{"time":6,"type":"word","start":0,"end":1,"value":"e"}
{"time":198,"type":"word","start":2,"end":14,"value":"Conservative"}
{"time":860,"type":"word","start":15,"end":22,"value":"Promise"}
{"time":1265,"type":"word","start":23,"end":26,"value":"THE"}
{"time":1368,"type":"word","start":27,"end":31,"value":"CASE"}
{"time":1677,"type":"word","start":32,"end":35,"value":"FOR"}
{"time":1827,"type":"word","start":36,"end":40,"value":"FREE"}
{"time":2084,"type":"word","start":41,"end":46,"value":"TRADE"}
{"time":2423,"type":"word","start":47,"end":51,"value":"Kent"}
{"time":2655,"type":"word","start":52,"end":59,"value":"Lassman"}
{"time":3079,"type":"word","start":60,"end":65,"value":"Trade"}
{"time":3346,"type":"word","start":66,"end":72,"value":"policy"}
{"time":3792,"type":"word","start":73,"end":75,"value":"is"}
{"time":3908,"type":"word","start":76,"end":81,"value":"about"}
{"time":4174,"type":"word","start":82,"end":86,"value":"more"}
{"time":4390,"type":"word","start":87,"end":91,"value":"than"}
{"time":4560,"type":"word","start":92,"end":97,"value":"goods"}
{"time":4874,"type":"word","start":98,"end":101,"value":"and"}
{"time":5011,"type":"word","start":102,"end":110,"value":"services"}
{"time":5851,"type":"word","start":112,"end":114,"value":"It"}
{"time":5971,"type":"word","start":115,"end":117,"value":"is"}
{"time":6101,"type":"word","start":118,"end":119,"value":"a"}
{"time":6152,"type":"word","start":120,"end":129,"value":"statement"}
{"time":6612,"type":"word","start":130,"end":132,"value":"of"}
{"time":6731,"type":"word","start":133,"end":138,"value":"Amer-"}
{"time":7031,"type":"word","start":139,"end":143,"value":"ican"}
{"time":7374,"type":"word","start":144,"end":152,"value":"identity"}
{"time":8365,"type":"word","start":154,"end":157,"value":"Our"}
{"time":8473,"type":"word","start":158,"end":163,"value":"trade"}
{"time":8785,"type":"word","start":164,"end":170,"value":"policy"}
{"time":9245,"type":"word","start":171,"end":178,"value":"choices"}
{"time":9734,"type":"word","start":179,"end":185,"value":"reveal"}
{"time":10139,"type":"word","start":186,"end":197,"value":"America’s"}
{"time":10611,"type":"word","start":198,"end":204,"value":"values"}
{"time":11064,"type":"word","start":205,"end":208,"value":"and"}
{"time":11181,"type":"word","start":209,"end":214,"value":"where"}
{"time":11297,"type":"word","start":215,"end":217,"value":"we"}
{"time":11435,"type":"word","start":218,"end":221,"value":"put"}
{"time":11629,"type":"word","start":222,"end":225,"value":"our"}
{"time":11734,"type":"word","start":226,"end":231,"value":"trust"}
{"time":12646,"type":"word","start":233,"end":235,"value":"Do"}
{"time":12778,"type":"word","start":236,"end":238,"value":"we"}
{"time":12887,"type":"word","start":239,"end":244,"value":"place"}
{"time":13191,"type":"word","start":245,"end":248,"value":"our"}
{"time":13312,"type":"word","start":249,"end":254,"value":"trust"}
{"time":13659,"type":"word","start":255,"end":257,"value":"in"}
{"time":13759,"type":"word","start":258,"end":268,"value":"Washington"}
{"time":14270,"type":"word","start":269,"end":275,"value":"elites"}
{"time":14634,"type":"word","start":276,"end":278,"value":"to"}
{"time":14756,"type":"word","start":279,"end":285,"value":"revive"}
{"time":15125,"type":"word","start":286,"end":287,"value":"a"}
{"time":15166,"type":"word","start":288,"end":297,"value":"declining"}
{"time":15675,"type":"word","start":298,"end":303,"value":"coun-"}
{"time":16040,"type":"word","start":304,"end":307,"value":"try"}
{"time":16682,"type":"word","start":309,"end":311,"value":"or"}
{"time":16796,"type":"word","start":312,"end":314,"value":"do"}
{"time":16894,"type":"word","start":315,"end":317,"value":"we"}
{"time":17004,"type":"word","start":318,"end":323,"value":"trust"}
{"time":17343,"type":"word","start":324,"end":326,"value":"in"}
{"time":17424,"type":"word","start":327,"end":338,"value":"America’s"}
{"time":17940,"type":"word","start":339,"end":348,"value":"tradition"}
{"time":18368,"type":"word","start":349,"end":351,"value":"of"}
{"time":18504,"type":"word","start":352,"end":365,"value":"entrepreneurs"}
{"time":19149,"type":"word","start":366,"end":369,"value":"and"}
{"time":19251,"type":"word","start":370,"end":378,"value":"everyday"}
{"time":19602,"type":"word","start":379,"end":385,"value":"people"}
{"time":19912,"type":"word","start":386,"end":393,"value":"blazing"}
{"time":20301,"type":"word","start":394,"end":397,"value":"new"}
{"time":20424,"type":"word","start":398,"end":404,"value":"trails"}
{"time":21420,"type":"word","start":406,"end":408,"value":"Do"}
{"time":21501,"type":"word","start":409,"end":411,"value":"we"}
{"time":21595,"type":"word","start":412,"end":418,"value":"follow"}
{"time":21955,"type":"word","start":419,"end":424,"value":"China"}
{"time":22284,"type":"word","start":425,"end":427,"value":"by"}
{"time":22433,"type":"word","start":428,"end":435,"value":"copying"}
{"time":22985,"type":"word","start":436,"end":439,"value":"its"}
{"time":23124,"type":"word","start":440,"end":450,"value":"strong-arm"}
{"time":23662,"type":"word","start":451,"end":456,"value":"trade"}
{"time":23975,"type":"word","start":457,"end":465,"value":"policies"}
{"time":24849,"type":"word","start":467,"end":469,"value":"or"}
{"time":25002,"type":"word","start":470,"end":472,"value":"do"}
{"time":25114,"type":"word","start":473,"end":475,"value":"we"}
{"time":25229,"type":"word","start":476,"end":480,"value":"lead"}
{"time":25458,"type":"word","start":481,"end":486,"value":"China"}
{"time":25831,"type":"word","start":487,"end":490,"value":"and"}
{"time":25936,"type":"word","start":491,"end":494,"value":"the"}
{"time":26029,"type":"word","start":495,"end":499,"value":"rest"}
{"time":26311,"type":"word","start":500,"end":502,"value":"of"}
{"time":26367,"type":"word","start":503,"end":506,"value":"the"}
{"time":26449,"type":"word","start":507,"end":512,"value":"world"}
{"time":26750,"type":"word","start":513,"end":515,"value":"by"}
{"time":26920,"type":"word","start":516,"end":523,"value":"forging"}
{"time":27369,"type":"word","start":524,"end":527,"value":"our"}
{"time":27533,"type":"word","start":528,"end":531,"value":"own"}
{"time":27711,"type":"word","start":532,"end":536,"value":"path"}
{"time":28573,"type":"word","start":538,"end":541,"value":"Our"}
{"time":28681,"type":"word","start":542,"end":547,"value":"trade"}
{"time":28993,"type":"word","start":548,"end":554,"value":"policy"}
{"time":29441,"type":"word","start":555,"end":564,"value":"decisions"}
{"time":29949,"type":"word","start":565,"end":569,"value":"will"}
{"time":30093,"type":"word","start":570,"end":574,"value":"tell"}
{"time":30277,"type":"word","start":575,"end":578,"value":"you"}
{"time":30410,"type":"word","start":579,"end":583,"value":"what"}
{"time":30599,"type":"word","start":584,"end":586,"value":"we"}
{"time":30754,"type":"word","start":587,"end":596,"value":"Americans"}
{"time":31248,"type":"word","start":597,"end":603,"value":"really"}
{"time":31489,"type":"word","start":604,"end":609,"value":"think"}
{"time":31737,"type":"word","start":610,"end":612,"value":"of"}
{"time":31837,"type":"word","start":613,"end":622,"value":"ourselves"}
{"time":32845,"type":"word","start":624,"end":625,"value":"A"}
{"time":32918,"type":"word","start":626,"end":638,"value":"CONSERVATIVE"}
{"time":33516,"type":"word","start":639,"end":645,"value":"VISION"}
{"time":33781,"type":"word","start":646,"end":649,"value":"FOR"}
{"time":33925,"type":"word","start":650,"end":655,"value":"TRADE"}
{"time":34241,"type":"word","start":656,"end":659,"value":"The"}
{"time":34308,"type":"word","start":660,"end":666,"value":"policy"}
{"time":34737,"type":"word","start":667,"end":682,"value":"recommendations"}
{"time":35564,"type":"word","start":683,"end":685,"value":"in"}
{"time":35653,"type":"word","start":686,"end":690,"value":"this"}
{"time":35799,"type":"word","start":691,"end":698,"value":"chapter"}
{"time":36159,"type":"word","start":699,"end":706,"value":"reflect"}
{"time":36603,"type":"word","start":707,"end":708,"value":"a"}
{"time":36641,"type":"word","start":709,"end":715,"value":"belief"}
{"time":37002,"type":"word","start":716,"end":718,"value":"in"}
{"time":37081,"type":"word","start":719,"end":722,"value":"the"}
{"time":37142,"type":"word","start":723,"end":731,"value":"strength"}
{"time":37582,"type":"word","start":732,"end":734,"value":"of"}
{"time":37681,"type":"word","start":735,"end":746,"value":"America’s"}
{"time":38169,"type":"word","start":747,"end":755,"value":"founding"}
{"time":38623,"type":"word","start":756,"end":768,"value":"institutions"}
{"time":39665,"type":"word","start":770,"end":773,"value":"its"}
{"time":39834,"type":"word","start":774,"end":781,"value":"economy"}
{"time":40597,"type":"word","start":783,"end":786,"value":"and"}
{"time":40725,"type":"word","start":787,"end":790,"value":"its"}
{"time":40864,"type":"word","start":791,"end":797,"value":"people"}
{"time":41694,"type":"word","start":799,"end":803,"value":"They"}
{"time":41792,"type":"word","start":804,"end":807,"value":"are"}
{"time":41888,"type":"word","start":808,"end":813,"value":"based"}
{"time":42228,"type":"word","start":814,"end":816,"value":"on"}
{"time":42379,"type":"word","start":817,"end":821,"value":"data"}
{"time":42659,"type":"word","start":822,"end":829,"value":"showing"}
{"time":43006,"type":"word","start":830,"end":837,"value":"decades"}
{"time":43465,"type":"word","start":838,"end":840,"value":"of"}
{"time":43556,"type":"word","start":841,"end":849,"value":"American"}
{"time":44041,"type":"word","start":850,"end":858,"value":"progress"}
{"time":44556,"type":"word","start":859,"end":863,"value":"with"}
{"time":44704,"type":"word","start":864,"end":867,"value":"all"}
{"time":44875,"type":"word","start":868,"end":872,"value":"that"}
{"time":45003,"type":"word","start":873,"end":877,"value":"this"}
{"time":45223,"type":"word","start":878,"end":885,"value":"implies"}
{"time":46289,"type":"word","start":887,"end":891,"value":"They"}
{"time":46443,"type":"word","start":892,"end":896,"value":"also"}
{"time":46744,"type":"word","start":897,"end":904,"value":"reflect"}
{"time":47159,"type":"word","start":905,"end":906,"value":"a"}
{"time":47211,"type":"word","start":907,"end":916,"value":"realistic"}
{"time":47811,"type":"word","start":917,"end":930,"value":"understanding"}
{"time":48367,"type":"word","start":931,"end":933,"value":"of"}
{"time":48454,"type":"word","start":934,"end":937,"value":"the"}
{"time":48528,"type":"word","start":938,"end":942,"value":"fact"}
{"time":48872,"type":"word","start":943,"end":947,"value":"that"}
{"time":49021,"type":"word","start":948,"end":953,"value":"trade"}
{"time":49296,"type":"word","start":954,"end":960,"value":"policy"}
{"time":49757,"type":"word","start":961,"end":964,"value":"has"}
{"time":49935,"type":"word","start":965,"end":972,"value":"limited"}
{"time":50268,"type":"word","start":973,"end":985,"value":"capabilities"}
{"time":51016,"type":"word","start":986,"end":989,"value":"and"}
{"time":51127,"type":"word","start":990,"end":992,"value":"is"}
{"time":51247,"type":"word","start":993,"end":1003,"value":"vulnerable"}
{"time":51755,"type":"word","start":1004,"end":1006,"value":"to"}
{"time":51870,"type":"word","start":1007,"end":1014,"value":"mission"}
{"time":52216,"type":"word","start":1015,"end":1020,"value":"creep"}
{"time":52564,"type":"word","start":1021,"end":1024,"value":"and"}
{"time":52728,"type":"word","start":1025,"end":1035,"value":"regulatory"}
{"time":53379,"type":"word","start":1036,"end":1043,"value":"capture"}
{"time":54302,"type":"word","start":1045,"end":1057,"value":"Policymakers"}
{"time":55178,"type":"word","start":1058,"end":1064,"value":"should"}
{"time":55371,"type":"word","start":1065,"end":1067,"value":"be"}
{"time":55480,"type":"word","start":1068,"end":1074,"value":"modest"}
{"time":55934,"type":"word","start":1075,"end":1080,"value":"about"}
{"time":56182,"type":"word","start":1081,"end":1085,"value":"what"}
{"time":56393,"type":"word","start":1086,"end":1090,"value":"they"}
{"time":56499,"type":"word","start":1091,"end":1094,"value":"can"}
{"time":56649,"type":"word","start":1095,"end":1105,"value":"accomplish"}
{"time":57219,"type":"word","start":1106,"end":1113,"value":"through"}
{"time":57427,"type":"word","start":1114,"end":1119,"value":"trade"}
{"time":57736,"type":"word","start":1120,"end":1126,"value":"policy"}
{"time":58265,"type":"word","start":1127,"end":1130,"value":"and"}
{"time":58365,"type":"word","start":1131,"end":1135,"value":"need"}
{"time":58566,"type":"word","start":1136,"end":1138,"value":"to"}
{"time":58718,"type":"word","start":1139,"end":1147,"value":"exercise"}
{"time":59277,"type":"word","start":1148,"end":1156,"value":"constant"}
{"time":59723,"type":"word","start":1157,"end":1166,"value":"vigilance"}
{"time":60205,"type":"word","start":1167,"end":1174,"value":"against"}
{"time":60521,"type":"word","start":1175,"end":1181,"value":"abuses"}
{"time":61583,"type":"word","start":1183,"end":1186,"value":"For"}
{"time":61808,"type":"word","start":1187,"end":1194,"value":"example"}
{"time":62588,"type":"word","start":1196,"end":1197,"value":"l"}
{"time":62737,"type":"word","start":1198,"end":1203,"value":"Trade"}
{"time":62981,"type":"word","start":1204,"end":1207,"value":"can"}
{"time":63140,"type":"word","start":1208,"end":1213,"value":"lower"}
{"time":63364,"type":"word","start":1214,"end":1222,"value":"consumer"}
{"time":63878,"type":"word","start":1223,"end":1229,"value":"prices"}
{"time":64333,"type":"word","start":1230,"end":1233,"value":"for"}
{"time":64533,"type":"word","start":1234,"end":1242,"value":"ordinary"}
{"time":65023,"type":"word","start":1243,"end":1252,"value":"Americans"}
{"time":65540,"type":"word","start":1253,"end":1256,"value":"and"}
{"time":65659,"type":"word","start":1257,"end":1261,"value":"open"}
{"time":65877,"type":"word","start":1262,"end":1265,"value":"new"}
{"time":66047,"type":"word","start":1266,"end":1273,"value":"markets"}
{"time":66493,"type":"word","start":1274,"end":1277,"value":"for"}
{"time":66689,"type":"word","start":1278,"end":1286,"value":"American"}
{"time":67188,"type":"word","start":1287,"end":1297,"value":"businesses"}
{"time":67765,"type":"word","start":1298,"end":1301,"value":"and"}
{"time":67877,"type":"word","start":1302,"end":1307,"value":"their"}
{"time":67987,"type":"word","start":1308,"end":1313,"value":"goods"}
{"time":68915,"type":"word","start":1315,"end":1316,"value":"l"}
{"time":69075,"type":"word","start":1317,"end":1322,"value":"Trade"}
{"time":69353,"type":"word","start":1323,"end":1326,"value":"can"}
{"time":69508,"type":"word","start":1327,"end":1331,"value":"help"}
{"time":69735,"type":"word","start":1332,"end":1340,"value":"American"}
{"time":70158,"type":"word","start":1341,"end":1348,"value":"workers"}
{"time":70576,"type":"word","start":1349,"end":1352,"value":"and"}
{"time":70690,"type":"word","start":1353,"end":1363,"value":"businesses"}
{"time":71219,"type":"word","start":1364,"end":1366,"value":"to"}
{"time":71303,"type":"word","start":1367,"end":1377,"value":"specialize"}
{"time":72020,"type":"word","start":1378,"end":1380,"value":"in"}
{"time":72101,"type":"word","start":1381,"end":1385,"value":"what"}
{"time":72303,"type":"word","start":1386,"end":1390,"value":"they"}
{"time":72419,"type":"word","start":1391,"end":1393,"value":"do"}
{"time":72630,"type":"word","start":1394,"end":1398,"value":"best"}
{"time":73260,"type":"word","start":1401,"end":1406,"value":"which"}
{"time":73441,"type":"word","start":1407,"end":1409,"value":"is"}
{"time":73543,"type":"word","start":1410,"end":1413,"value":"how"}
{"time":73686,"type":"word","start":1414,"end":1418,"value":"they"}
{"time":73816,"type":"word","start":1419,"end":1429,"value":"outcompete"}
{"time":74374,"type":"word","start":1430,"end":1433,"value":"the"}
{"time":74457,"type":"word","start":1434,"end":1438,"value":"rest"}
{"time":74780,"type":"word","start":1439,"end":1441,"value":"of"}
{"time":74836,"type":"word","start":1442,"end":1445,"value":"the"}
{"time":74918,"type":"word","start":1446,"end":1451,"value":"world"}
{"time":75244,"type":"word","start":1452,"end":1454,"value":"in"}
{"time":75343,"type":"word","start":1455,"end":1465,"value":"technology"}
{"time":76300,"type":"word","start":1467,"end":1480,"value":"manufacturing"}
{"time":77454,"type":"word","start":1482,"end":1493,"value":"agriculture"}
{"time":78478,"type":"word","start":1495,"end":1498,"value":"and"}
{"time":78620,"type":"word","start":1499,"end":1504,"value":"other"}
{"time":78847,"type":"word","start":1505,"end":1510,"value":"areas"}
{"time":79703,"type":"word","start":1512,"end":1513,"value":"l"}
{"time":79886,"type":"word","start":1514,"end":1516,"value":"In"}
{"time":79991,"type":"word","start":1517,"end":1524,"value":"foreign"}
{"time":80370,"type":"word","start":1525,"end":1531,"value":"policy"}
{"time":81175,"type":"word","start":1533,"end":1538,"value":"trade"}
{"time":81483,"type":"word","start":1539,"end":1542,"value":"can"}
{"time":81650,"type":"word","start":1543,"end":1547,"value":"help"}
{"time":81896,"type":"word","start":1548,"end":1550,"value":"to"}
{"time":81985,"type":"word","start":1551,"end":1559,"value":"preserve"}
{"time":82381,"type":"word","start":1560,"end":1563,"value":"and"}
{"time":82490,"type":"word","start":1564,"end":1574,"value":"strengthen"}
{"time":83010,"type":"word","start":1575,"end":1584,"value":"alliances"}
{"time":84162,"type":"word","start":1586,"end":1588,"value":"At"}
{"time":84300,"type":"word","start":1589,"end":1592,"value":"the"}
{"time":84373,"type":"word","start":1593,"end":1597,"value":"same"}
{"time":84672,"type":"word","start":1598,"end":1602,"value":"time"}
{"time":85303,"type":"word","start":1604,"end":1609,"value":"sound"}
{"time":85647,"type":"word","start":1610,"end":1615,"value":"trade"}
{"time":85900,"type":"word","start":1616,"end":1622,"value":"policy"}
{"time":86406,"type":"word","start":1623,"end":1631,"value":"requires"}
{"time":86936,"type":"word","start":1632,"end":1640,"value":"humility"}
{"time":87949,"type":"word","start":1642,"end":1644,"value":"It"}
{"time":88061,"type":"word","start":1645,"end":1647,"value":"is"}
{"time":88204,"type":"word","start":1648,"end":1651,"value":"not"}
{"time":88412,"type":"word","start":1652,"end":1653,"value":"a"}
{"time":88462,"type":"word","start":1654,"end":1661,"value":"panacea"}
{"time":89039,"type":"word","start":1662,"end":1665,"value":"for"}
{"time":89239,"type":"word","start":1666,"end":1671,"value":"every"}
{"time":89448,"type":"word","start":1672,"end":1678,"value":"policy"}
{"time":89912,"type":"word","start":1679,"end":1686,"value":"problem"}
{"time":90921,"type":"word","start":1688,"end":1693,"value":"Trade"}
{"time":91205,"type":"word","start":1694,"end":1700,"value":"policy"}
{"time":91636,"type":"word","start":1701,"end":1707,"value":"cannot"}
{"time":91942,"type":"word","start":1708,"end":1713,"value":"favor"}
{"time":92277,"type":"word","start":1714,"end":1717,"value":"one"}
{"time":92552,"type":"word","start":1718,"end":1724,"value":"sector"}
{"time":92991,"type":"word","start":1725,"end":1729,"value":"over"}
{"time":93211,"type":"word","start":1730,"end":1737,"value":"another"}
{"time":93481,"type":"word","start":1738,"end":1745,"value":"without"}
{"time":93804,"type":"word","start":1746,"end":1753,"value":"causing"}
{"time":94206,"type":"word","start":1754,"end":1763,"value":"tradeoffs"}
{"time":94770,"type":"word","start":1764,"end":1768,"value":"that"}
{"time":94902,"type":"word","start":1769,"end":1777,"value":"outweigh"}
{"time":95304,"type":"word","start":1778,"end":1781,"value":"the"}
{"time":95406,"type":"word","start":1782,"end":1793,"value":"benefits.41"}
{"time":96808,"type":"word","start":1794,"end":1801,"value":"Neither"}
{"time":97092,"type":"word","start":1802,"end":1806,"value":"free"}
{"time":97343,"type":"word","start":1807,"end":1812,"value":"trade"}
{"time":97654,"type":"word","start":1813,"end":1816,"value":"nor"}
{"time":97828,"type":"word","start":1817,"end":1830,"value":"protectionism"}
{"time":98562,"type":"word","start":1831,"end":1835,"value":"will"}
{"time":98751,"type":"word","start":1836,"end":1842,"value":"create"}
{"time":99143,"type":"word","start":1843,"end":1847,"value":"jobs"}
{"time":100031,"type":"word","start":1849,"end":1854,"value":"Trade"}
{"time":100284,"type":"word","start":1855,"end":1862,"value":"affects"}
{"time":100663,"type":"word","start":1863,"end":1866,"value":"the"}
{"time":100749,"type":"word","start":1867,"end":1872,"value":"types"}
{"time":101104,"type":"word","start":1873,"end":1875,"value":"of"}
{"time":101211,"type":"word","start":1876,"end":1880,"value":"jobs"}
{"time":101586,"type":"word","start":1881,"end":1887,"value":"people"}
{"time":101861,"type":"word","start":1888,"end":1892,"value":"have"}
{"time":102482,"type":"word","start":1894,"end":1897,"value":"but"}
{"time":102671,"type":"word","start":1898,"end":1900,"value":"it"}
{"time":102748,"type":"word","start":1901,"end":1904,"value":"has"}
{"time":102929,"type":"word","start":1905,"end":1907,"value":"no"}
{"time":103065,"type":"word","start":1908,"end":1916,"value":"long-run"}
{"time":103516,"type":"word","start":1917,"end":1923,"value":"effect"}
{"time":103893,"type":"word","start":1924,"end":1926,"value":"on"}
{"time":103989,"type":"word","start":1927,"end":1930,"value":"the"}
{"time":104057,"type":"word","start":1931,"end":1937,"value":"number"}
{"time":104389,"type":"word","start":1938,"end":1940,"value":"of"}
{"time":104468,"type":"word","start":1941,"end":1945,"value":"jobs"}
{"time":105353,"type":"word","start":1947,"end":1952,"value":"Labor"}
{"time":105627,"type":"word","start":1953,"end":1958,"value":"force"}
{"time":105967,"type":"word","start":1959,"end":1963,"value":"size"}
{"time":106311,"type":"word","start":1964,"end":1966,"value":"is"}
{"time":106446,"type":"word","start":1967,"end":1971,"value":"tied"}
{"time":106716,"type":"word","start":1972,"end":1974,"value":"to"}
{"time":106799,"type":"word","start":1975,"end":1985,"value":"population"}
{"time":107488,"type":"word","start":1986,"end":1990,"value":"size"}
{"time":107864,"type":"word","start":1991,"end":1995,"value":"more"}
{"time":108053,"type":"word","start":1996,"end":2000,"value":"than"}
{"time":108224,"type":"word","start":2001,"end":2009,"value":"anything"}
{"time":108631,"type":"word","start":2010,"end":2014,"value":"else"}
{"time":109433,"type":"word","start":2016,"end":2019,"value":"The"}
{"time":109565,"type":"word","start":2020,"end":2028,"value":"American"}
{"time":110022,"type":"word","start":2029,"end":2035,"value":"people"}
{"time":110341,"type":"word","start":2036,"end":2039,"value":"are"}
{"time":110457,"type":"word","start":2040,"end":2045,"value":"smart"}
{"time":110816,"type":"word","start":2046,"end":2049,"value":"and"}
{"time":110945,"type":"word","start":2050,"end":2063,"value":"sophisticated"}
{"time":111743,"type":"word","start":2064,"end":2070,"value":"enough"}
{"time":111995,"type":"word","start":2071,"end":2073,"value":"to"}
{"time":112110,"type":"word","start":2074,"end":2078,"value":"hear"}
{"time":112281,"type":"word","start":2079,"end":2084,"value":"these"}
{"time":112498,"type":"word","start":2085,"end":2091,"value":"truths"}
{"time":113458,"type":"word","start":2093,"end":2095,"value":"It"}
{"time":113571,"type":"word","start":2096,"end":2098,"value":"is"}
{"time":113714,"type":"word","start":2099,"end":2102,"value":"not"}
{"time":113952,"type":"word","start":2103,"end":2107,"value":"just"}
{"time":114160,"type":"word","start":2108,"end":2121,"value":"conservatives"}
{"time":114857,"type":"word","start":2122,"end":2125,"value":"who"}
{"time":114963,"type":"word","start":2126,"end":2138,"value":"overestimate"}
{"time":115627,"type":"word","start":2139,"end":2142,"value":"the"}
{"time":115704,"type":"word","start":2143,"end":2148,"value":"power"}
{"time":116052,"type":"word","start":2149,"end":2151,"value":"of"}
{"time":116131,"type":"word","start":2152,"end":2157,"value":"trade"}
{"time":116449,"type":"word","start":2158,"end":2164,"value":"policy"}
{"time":117458,"type":"word","start":2166,"end":2172,"value":"Recent"}
{"time":117819,"type":"word","start":2173,"end":2184,"value":"progressive"}
{"time":118291,"type":"word","start":2185,"end":2193,"value":"attempts"}
{"time":118665,"type":"word","start":2194,"end":2196,"value":"to"}
{"time":118775,"type":"word","start":2197,"end":2200,"value":"use"}
{"time":119007,"type":"word","start":2201,"end":2206,"value":"trade"}
{"time":119319,"type":"word","start":2207,"end":2213,"value":"policy"}
{"time":119806,"type":"word","start":2214,"end":2216,"value":"to"}
{"time":119960,"type":"word","start":2217,"end":2224,"value":"advance"}
{"time":120360,"type":"word","start":2225,"end":2244,"value":"whole-of-government"}
{"time":121171,"type":"word","start":2245,"end":2252,"value":"initia-"}
{"time":121708,"type":"word","start":2253,"end":2258,"value":"tives"}
{"time":121917,"type":"word","start":2259,"end":2261,"value":"on"}
{"time":122043,"type":"word","start":2262,"end":2269,"value":"climate"}
{"time":122679,"type":"word","start":2271,"end":2277,"value":"equity"}
{"time":123374,"type":"word","start":2279,"end":2282,"value":"and"}
{"time":123508,"type":"word","start":2283,"end":2288,"value":"other"}
{"time":123789,"type":"word","start":2289,"end":2295,"value":"issues"}
{"time":124155,"type":"word","start":2296,"end":2300,"value":"will"}
{"time":124292,"type":"word","start":2301,"end":2305,"value":"fail"}
{"time":124639,"type":"word","start":2306,"end":2309,"value":"for"}
{"time":124787,"type":"word","start":2310,"end":2313,"value":"the"}
{"time":124875,"type":"word","start":2314,"end":2318,"value":"same"}
{"time":125176,"type":"word","start":2319,"end":2325,"value":"reason"}
{"time":125557,"type":"word","start":2326,"end":2330,"value":"that"}
{"time":125677,"type":"word","start":2331,"end":2332,"value":"a"}
{"time":125744,"type":"word","start":2333,"end":2339,"value":"hammer"}
{"time":126041,"type":"word","start":2340,"end":2346,"value":"cannot"}
{"time":126364,"type":"word","start":2347,"end":2351,"value":"turn"}
{"time":126586,"type":"word","start":2352,"end":2353,"value":"a"}
{"time":126635,"type":"word","start":2354,"end":2359,"value":"screw"}
{"time":127390,"type":"word","start":2361,"end":2363,"value":"It"}
{"time":127502,"type":"word","start":2364,"end":2366,"value":"is"}
{"time":127618,"type":"word","start":2367,"end":2370,"value":"the"}
{"time":127732,"type":"word","start":2371,"end":2376,"value":"wrong"}
{"time":128004,"type":"word","start":2377,"end":2381,"value":"tool"}
{"time":128248,"type":"word","start":2382,"end":2385,"value":"for"}
{"time":128389,"type":"word","start":2386,"end":2389,"value":"the"}
{"time":128487,"type":"word","start":2390,"end":2393,"value":"job"}
{"time":129324,"type":"word","start":2395,"end":2408,"value":"Conservatives"}
{"time":130019,"type":"word","start":2409,"end":2415,"value":"should"}
{"time":130218,"type":"word","start":2416,"end":2418,"value":"be"}
{"time":130301,"type":"word","start":2419,"end":2423,"value":"sim-"}
{"time":130559,"type":"word","start":2424,"end":2430,"value":"ilarly"}
{"time":130905,"type":"word","start":2431,"end":2440,"value":"skeptical"}
{"time":131511,"type":"word","start":2441,"end":2443,"value":"of"}
{"time":131623,"type":"word","start":2444,"end":2450,"value":"recent"}
{"time":131954,"type":"word","start":2451,"end":2459,"value":"attempts"}
{"time":132373,"type":"word","start":2460,"end":2462,"value":"on"}
{"time":132474,"type":"word","start":2463,"end":2466,"value":"the"}
{"time":132544,"type":"word","start":2467,"end":2472,"value":"Right"}
{"time":132766,"type":"word","start":2473,"end":2475,"value":"to"}
{"time":132843,"type":"word","start":2476,"end":2479,"value":"use"}
{"time":133120,"type":"word","start":2480,"end":2491,"value":"progressive"}
{"time":133647,"type":"word","start":2492,"end":2497,"value":"trade"}
{"time":133978,"type":"word","start":2498,"end":2504,"value":"policy"}
{"time":134503,"type":"word","start":2505,"end":2507,"value":"to"}
{"time":134620,"type":"word","start":2508,"end":2514,"value":"punish"}
{"time":134952,"type":"word","start":2515,"end":2524,"value":"political"}
{"time":135436,"type":"word","start":2525,"end":2534,"value":"opponents"}
{"time":136177,"type":"word","start":2536,"end":2542,"value":"remake"}
{"time":136572,"type":"word","start":2543,"end":2556,"value":"manufacturing"}
{"time":137679,"type":"word","start":2558,"end":2560,"value":"or"}
{"time":137827,"type":"word","start":2561,"end":2571,"value":"accomplish"}
{"time":138412,"type":"word","start":2572,"end":2577,"value":"other"}
{"time":138640,"type":"word","start":2578,"end":2588,"value":"objectives"}
{"time":139695,"type":"word","start":2590,"end":2593,"value":"—"}
{"time":140532,"type":"word","start":2594,"end":2597,"value":"797"}
{"time":142210,"type":"word","start":2602,"end":2606,"value":"2025"}
{"time":143117,"type":"word","start":2607,"end":2619,"value":"Presidential"}
{"time":143700,"type":"word","start":2620,"end":2630,"value":"Transition"}
{"time":144327,"type":"word","start":2631,"end":2638,"value":"Project"}
{"time":144790,"type":"word","start":2639,"end":2642,"value":"for"}
{"time":144940,"type":"word","start":2643,"end":2648,"value":"which"}
{"time":145163,"type":"word","start":2649,"end":2651,"value":"it"}
{"time":145250,"type":"word","start":2652,"end":2654,"value":"is"}
{"time":145361,"type":"word","start":2655,"end":2658,"value":"not"}
{"time":145569,"type":"word","start":2659,"end":2665,"value":"suited"}
{"time":146386,"type":"word","start":2667,"end":2670,"value":"The"}
{"time":146480,"type":"word","start":2671,"end":2675,"value":"next"}
{"time":146811,"type":"word","start":2676,"end":2690,"value":"Administration"}
{"time":147555,"type":"word","start":2691,"end":2696,"value":"needs"}
{"time":147807,"type":"word","start":2697,"end":2699,"value":"to"}
{"time":147996,"type":"word","start":2700,"end":2703,"value":"end"}
{"time":148125,"type":"word","start":2704,"end":2707,"value":"the"}
{"time":148205,"type":"word","start":2708,"end":2715,"value":"mission"}
{"time":148550,"type":"word","start":2716,"end":2721,"value":"creep"}
{"time":148815,"type":"word","start":2722,"end":2726,"value":"that"}
{"time":148936,"type":"word","start":2727,"end":2730,"value":"has"}
{"time":149075,"type":"word","start":2731,"end":2734,"value":"all"}
{"time":149280,"type":"word","start":2735,"end":2738,"value":"but"}
{"time":149451,"type":"word","start":2739,"end":2744,"value":"taken"}
{"time":149726,"type":"word","start":2745,"end":2749,"value":"over"}
{"time":149953,"type":"word","start":2750,"end":2755,"value":"trade"}
{"time":150265,"type":"word","start":2756,"end":2762,"value":"policy"}
{"time":150703,"type":"word","start":2763,"end":2765,"value":"in"}
{"time":150800,"type":"word","start":2766,"end":2772,"value":"recent"}
{"time":151137,"type":"word","start":2773,"end":2778,"value":"years"}
{"time":151945,"type":"word","start":2780,"end":2785,"value":"Trade"}
{"time":152202,"type":"word","start":2786,"end":2792,"value":"policy"}
{"time":152706,"type":"word","start":2793,"end":2798,"value":"works"}
{"time":153044,"type":"word","start":2799,"end":2803,"value":"best"}
{"time":153305,"type":"word","start":2804,"end":2808,"value":"when"}
{"time":153444,"type":"word","start":2809,"end":2811,"value":"it"}
{"time":153534,"type":"word","start":2812,"end":2818,"value":"sticks"}
{"time":153862,"type":"word","start":2819,"end":2821,"value":"to"}
{"time":153981,"type":"word","start":2822,"end":2827,"value":"trade"}
{"time":154268,"type":"word","start":2828,"end":2831,"value":"and"}
{"time":154374,"type":"word","start":2832,"end":2838,"value":"treats"}
{"time":154681,"type":"word","start":2839,"end":2847,"value":"separate"}
{"time":155008,"type":"word","start":2848,"end":2854,"value":"issues"}
{"time":155334,"type":"word","start":2855,"end":2865,"value":"separately"}
{"time":156333,"type":"word","start":2867,"end":2872,"value":"Trade"}
{"time":156573,"type":"word","start":2873,"end":2883,"value":"agreements"}
{"time":157060,"type":"word","start":2884,"end":2889,"value":"since"}
{"time":157335,"type":"word","start":2890,"end":2893,"value":"the"}
{"time":157430,"type":"word","start":2894,"end":2899,"value":"North"}
{"time":157725,"type":"word","start":2900,"end":2908,"value":"American"}
{"time":158164,"type":"word","start":2909,"end":2913,"value":"Free"}
{"time":158398,"type":"word","start":2914,"end":2919,"value":"Trade"}
{"time":158683,"type":"word","start":2920,"end":2929,"value":"Agreement"}
{"time":159480,"type":"word","start":2931,"end":2936,"value":"NAFTA"}
{"time":160214,"type":"word","start":2938,"end":2942,"value":"have"}
{"time":160358,"type":"word","start":2943,"end":2947,"value":"been"}
{"time":160503,"type":"word","start":2948,"end":2960,"value":"increasingly"}
{"time":161088,"type":"word","start":2961,"end":2969,"value":"burdened"}
{"time":161448,"type":"word","start":2970,"end":2972,"value":"by"}
{"time":161610,"type":"word","start":2973,"end":2988,"value":"trade-unrelated"}
{"time":162316,"type":"word","start":2989,"end":2999,"value":"provisions"}
{"time":162844,"type":"word","start":3000,"end":3009,"value":"involving"}
{"time":163289,"type":"word","start":3010,"end":3012,"value":"la"}
