{"time":6,"type":"word","start":0,"end":3,"value":"ams"}
{"time":227,"type":"word","start":4,"end":13,"value":"including"}
{"time":645,"type":"word","start":14,"end":16,"value":"by"}
{"time":819,"type":"word","start":17,"end":28,"value":"encouraging"}
{"time":1316,"type":"word","start":29,"end":32,"value":"the"}
{"time":1402,"type":"word","start":33,"end":37,"value":"role"}
{"time":1691,"type":"word","start":38,"end":40,"value":"of"}
{"time":1776,"type":"word","start":41,"end":50,"value":"religious"}
{"time":2169,"type":"word","start":51,"end":64,"value":"organizations"}
{"time":2935,"type":"word","start":65,"end":67,"value":"in"}
{"time":3025,"type":"word","start":68,"end":75,"value":"appren-"}
{"time":3310,"type":"word","start":76,"end":85,"value":"ticeships"}
{"time":4077,"type":"word","start":87,"end":93,"value":"making"}
{"time":4439,"type":"word","start":94,"end":111,"value":"family-sustaining"}
{"time":5367,"type":"word","start":112,"end":116,"value":"jobs"}
{"time":5734,"type":"word","start":117,"end":127,"value":"accessible"}
{"time":6586,"type":"word","start":129,"end":140,"value":"simplifying"}
{"time":7235,"type":"word","start":141,"end":151,"value":"employment"}
{"time":7739,"type":"word","start":152,"end":164,"value":"requirements"}
{"time":8638,"type":"word","start":166,"end":169,"value":"and"}
{"time":8739,"type":"word","start":170,"end":178,"value":"allowing"}
{"time":9143,"type":"word","start":179,"end":188,"value":"employers"}
{"time":9690,"type":"word","start":189,"end":191,"value":"to"}
{"time":9800,"type":"word","start":192,"end":198,"value":"prefer"}
{"time":10154,"type":"word","start":199,"end":207,"value":"American"}
{"time":10617,"type":"word","start":208,"end":216,"value":"citizens"}
{"time":11158,"type":"word","start":217,"end":221,"value":"when"}
{"time":11336,"type":"word","start":222,"end":228,"value":"making"}
{"time":11647,"type":"word","start":229,"end":235,"value":"hiring"}
{"time":12023,"type":"word","start":236,"end":245,"value":"decisions"}
{"time":12852,"type":"word","start":247,"end":252,"value":"among"}
{"time":13117,"type":"word","start":253,"end":256,"value":"the"}
{"time":13253,"type":"word","start":257,"end":262,"value":"other"}
{"time":13424,"type":"word","start":263,"end":269,"value":"policy"}
{"time":13936,"type":"word","start":270,"end":285,"value":"recommendations"}
{"time":14732,"type":"word","start":286,"end":295,"value":"discussed"}
{"time":15244,"type":"word","start":296,"end":301,"value":"above"}
{"time":15966,"type":"word","start":303,"end":305,"value":"we"}
{"time":16091,"type":"word","start":306,"end":309,"value":"can"}
{"time":16279,"type":"word","start":310,"end":315,"value":"begin"}
{"time":16545,"type":"word","start":316,"end":318,"value":"to"}
{"time":16633,"type":"word","start":319,"end":325,"value":"secure"}
{"time":17056,"type":"word","start":326,"end":327,"value":"a"}
{"time":17087,"type":"word","start":328,"end":334,"value":"future"}
{"time":17493,"type":"word","start":335,"end":337,"value":"in"}
{"time":17591,"type":"word","start":338,"end":343,"value":"which"}
{"time":17828,"type":"word","start":344,"end":347,"value":"the"}
{"time":17961,"type":"word","start":348,"end":356,"value":"American"}
{"time":18399,"type":"word","start":357,"end":363,"value":"worker"}
{"time":19065,"type":"word","start":365,"end":368,"value":"and"}
{"time":19202,"type":"word","start":369,"end":371,"value":"by"}
{"time":19369,"type":"word","start":372,"end":381,"value":"extension"}
{"time":19890,"type":"word","start":382,"end":385,"value":"the"}
{"time":19989,"type":"word","start":386,"end":394,"value":"American"}
{"time":20457,"type":"word","start":395,"end":401,"value":"family"}
{"time":21159,"type":"word","start":403,"end":406,"value":"can"}
{"time":21334,"type":"word","start":407,"end":413,"value":"thrive"}
{"time":21688,"type":"word","start":414,"end":417,"value":"and"}
{"time":21787,"type":"word","start":418,"end":425,"value":"prosper"}
{"time":22731,"type":"word","start":427,"end":437,"value":"AUTHOR’S"}
{"time":23080,"type":"word","start":438,"end":442,"value":"NOTE"}
{"time":23638,"type":"word","start":444,"end":448,"value":"Many"}
{"time":23914,"type":"word","start":449,"end":461,"value":"contributors"}
{"time":24845,"type":"word","start":463,"end":469,"value":"listed"}
{"time":25247,"type":"word","start":470,"end":472,"value":"at"}
{"time":25342,"type":"word","start":473,"end":476,"value":"the"}
{"time":25418,"type":"word","start":477,"end":482,"value":"front"}
{"time":25673,"type":"word","start":483,"end":485,"value":"of"}
{"time":25744,"type":"word","start":486,"end":490,"value":"this"}
{"time":25922,"type":"word","start":491,"end":497,"value":"volume"}
{"time":26696,"type":"word","start":499,"end":506,"value":"deserve"}
{"time":27091,"type":"word","start":507,"end":513,"value":"credit"}
{"time":27439,"type":"word","start":514,"end":517,"value":"for"}
{"time":27577,"type":"word","start":518,"end":522,"value":"this"}
{"time":27752,"type":"word","start":523,"end":527,"value":"work"}
{"time":28387,"type":"word","start":529,"end":532,"value":"but"}
{"time":28571,"type":"word","start":533,"end":537,"value":"Oren"}
{"time":28858,"type":"word","start":538,"end":542,"value":"Cass"}
{"time":29563,"type":"word","start":544,"end":550,"value":"Rachel"}
{"time":29919,"type":"word","start":551,"end":559,"value":"Greszler"}
{"time":30734,"type":"word","start":561,"end":567,"value":"Rachel"}
{"time":31115,"type":"word","start":568,"end":576,"value":"Morrison"}
{"time":31875,"type":"word","start":578,"end":583,"value":"Caleb"}
{"time":32304,"type":"word","start":584,"end":587,"value":"Orr"}
{"time":32839,"type":"word","start":589,"end":592,"value":"and"}
{"time":33004,"type":"word","start":593,"end":601,"value":"Jonathan"}
{"time":33410,"type":"word","start":602,"end":609,"value":"Wolfson"}
{"time":33829,"type":"word","start":610,"end":617,"value":"deserve"}
{"time":34179,"type":"word","start":618,"end":625,"value":"special"}
{"time":34596,"type":"word","start":626,"end":633,"value":"mention"}
{"time":35572,"type":"word","start":635,"end":638,"value":"The"}
{"time":35721,"type":"word","start":639,"end":645,"value":"author"}
{"time":36022,"type":"word","start":646,"end":651,"value":"alone"}
{"time":36327,"type":"word","start":652,"end":659,"value":"assumes"}
{"time":36763,"type":"word","start":660,"end":674,"value":"responsibility"}
{"time":37607,"type":"word","start":675,"end":678,"value":"for"}
{"time":37759,"type":"word","start":679,"end":682,"value":"the"}
{"time":37847,"type":"word","start":683,"end":690,"value":"content"}
{"time":38345,"type":"word","start":691,"end":693,"value":"of"}
{"time":38402,"type":"word","start":694,"end":698,"value":"this"}
{"time":38605,"type":"word","start":699,"end":706,"value":"chapter"}
{"time":39300,"type":"word","start":708,"end":711,"value":"and"}
{"time":39444,"type":"word","start":712,"end":714,"value":"no"}
{"time":39592,"type":"word","start":715,"end":720,"value":"views"}
{"time":39890,"type":"word","start":721,"end":730,"value":"expressed"}
{"time":40367,"type":"word","start":731,"end":737,"value":"herein"}
{"time":40694,"type":"word","start":738,"end":744,"value":"should"}
{"time":40885,"type":"word","start":745,"end":747,"value":"be"}
{"time":40993,"type":"word","start":748,"end":758,"value":"attributed"}
{"time":41484,"type":"word","start":759,"end":761,"value":"to"}
{"time":41651,"type":"word","start":762,"end":765,"value":"any"}
{"time":41862,"type":"word","start":766,"end":771,"value":"other"}
{"time":42088,"type":"word","start":772,"end":782,"value":"individual"}
{"time":42768,"type":"word","start":785,"end":788,"value":"—"}
{"time":43355,"type":"word","start":789,"end":792,"value":"617"}
{"time":45020,"type":"word","start":797,"end":801,"value":"2025"}
{"time":45938,"type":"word","start":802,"end":814,"value":"Presidential"}
{"time":46521,"type":"word","start":815,"end":825,"value":"Transition"}
{"time":47131,"type":"word","start":826,"end":833,"value":"Project"}
{"time":47633,"type":"word","start":834,"end":842,"value":"ENDNOTES"}
{"time":48076,"type":"word","start":843,"end":844,"value":"1"}
{"time":48887,"type":"word","start":846,"end":854,"value":"Gretchen"}
{"time":49263,"type":"word","start":855,"end":865,"value":"Livingston"}
{"time":49760,"type":"word","start":866,"end":869,"value":"and"}
{"time":49859,"type":"word","start":870,"end":874,"value":"Anna"}
{"time":50068,"type":"word","start":875,"end":880,"value":"Brown"}
{"time":50782,"type":"word","start":885,"end":898,"value":"Intermarriage"}
{"time":51383,"type":"word","start":899,"end":901,"value":"in"}
{"time":51460,"type":"word","start":902,"end":905,"value":"the"}
{"time":51512,"type":"word","start":906,"end":909,"value":"U.S"}
{"time":51979,"type":"word","start":911,"end":916,"value":"Fifty"}
{"time":52283,"type":"word","start":917,"end":922,"value":"Years"}
{"time":52637,"type":"word","start":923,"end":928,"value":"after"}
{"time":52914,"type":"word","start":929,"end":935,"value":"Loving"}
{"time":53249,"type":"word","start":936,"end":937,"value":"v"}
{"time":54041,"type":"word","start":939,"end":947,"value":"Virginia"}
{"time":54816,"type":"word","start":952,"end":955,"value":"Pew"}
{"time":55007,"type":"word","start":956,"end":964,"value":"Research"}
{"time":55445,"type":"word","start":965,"end":971,"value":"Center"}
{"time":56048,"type":"word","start":973,"end":976,"value":"May"}
{"time":56229,"type":"word","start":977,"end":979,"value":"18"}
{"time":56701,"type":"word","start":981,"end":985,"value":"2017"}
{"time":57873,"type":"word","start":987,"end":998,"value":"https:\/\/www"}
{"time":59808,"type":"word","start":987,"end":1061,"value":"https:\/\/www.pewresearch.org\/social-trends\/2017\/05\/18\/intermarriage-in-the-"}
{"time":67183,"type":"word","start":1062,"end":1099,"value":"u-s-50-years-after-loving-v-virginia\/"}
{"time":70112,"type":"word","start":1101,"end":1109,"value":"accessed"}
{"time":70584,"type":"word","start":1110,"end":1115,"value":"March"}
{"time":70859,"type":"word","start":1116,"end":1117,"value":"4"}
{"time":71145,"type":"word","start":1119,"end":1123,"value":"2023"}
{"time":72587,"type":"word","start":1126,"end":1127,"value":"2"}
{"time":73357,"type":"word","start":1129,"end":1138,"value":"President"}
{"time":73756,"type":"word","start":1139,"end":1145,"value":"Lyndon"}
{"time":74052,"type":"word","start":1146,"end":1148,"value":"B."}
{"time":74217,"type":"word","start":1149,"end":1156,"value":"Johnson"}
{"time":74969,"type":"word","start":1158,"end":1167,"value":"Executive"}
{"time":75527,"type":"word","start":1168,"end":1173,"value":"Order"}
{"time":75828,"type":"word","start":1174,"end":1179,"value":"11246"}
{"time":78103,"type":"word","start":1184,"end":1189,"value":"Equal"}
{"time":78383,"type":"word","start":1190,"end":1200,"value":"Employment"}
{"time":78841,"type":"word","start":1201,"end":1212,"value":"Opportunity"}
{"time":79806,"type":"word","start":1217,"end":1228,"value":"https:\/\/www"}
{"time":83460,"type":"word","start":1230,"end":1310,"value":"presidency.ucsb.edu\/documents\/executive-order-11246-equal-employment-opportunity"}
{"time":90284,"type":"word","start":1312,"end":1320,"value":"accessed"}
{"time":90772,"type":"word","start":1321,"end":1326,"value":"March"}
{"time":91038,"type":"word","start":1327,"end":1328,"value":"7"}
{"time":91412,"type":"word","start":1330,"end":1334,"value":"2023"}
{"time":92880,"type":"word","start":1337,"end":1338,"value":"3"}
{"time":93831,"type":"word","start":1340,"end":1349,"value":"Pregnancy"}
{"time":94326,"type":"word","start":1350,"end":1364,"value":"Discrimination"}
{"time":95054,"type":"word","start":1365,"end":1368,"value":"Act"}
{"time":95295,"type":"word","start":1369,"end":1371,"value":"of"}
{"time":95372,"type":"word","start":1372,"end":1376,"value":"1978"}
{"time":96673,"type":"word","start":1378,"end":1384,"value":"Public"}
{"time":96980,"type":"word","start":1385,"end":1388,"value":"Law"}
{"time":97563,"type":"word","start":1390,"end":1392,"value":"95"}
{"time":98203,"type":"word","start":1392,"end":1393,"value":"-"}
{"time":98294,"type":"word","start":1393,"end":1396,"value":"555"}
{"time":100088,"type":"word","start":1398,"end":1401,"value":"The"}
{"time":100169,"type":"word","start":1402,"end":1411,"value":"Pregnancy"}
{"time":100690,"type":"word","start":1412,"end":1426,"value":"Discrimination"}
{"time":101418,"type":"word","start":1427,"end":1430,"value":"Act"}
{"time":101677,"type":"word","start":1431,"end":1438,"value":"amended"}
{"time":102019,"type":"word","start":1439,"end":1444,"value":"Title"}
{"time":102346,"type":"word","start":1445,"end":1448,"value":"VII"}
{"time":102651,"type":"word","start":1449,"end":1451,"value":"of"}
{"time":102741,"type":"word","start":1452,"end":1455,"value":"the"}
{"time":102818,"type":"word","start":1456,"end":1461,"value":"Civil"}
{"time":103130,"type":"word","start":1462,"end":1468,"value":"Rights"}
{"time":103487,"type":"word","start":1469,"end":1472,"value":"Act"}
{"time":103719,"type":"word","start":1473,"end":1475,"value":"of"}
{"time":103829,"type":"word","start":1476,"end":1480,"value":"1964"}
{"time":105376,"type":"word","start":1482,"end":1483,"value":"4"}
{"time":106371,"type":"word","start":1485,"end":1497,"value":"Consolidated"}
{"time":107150,"type":"word","start":1498,"end":1512,"value":"Appropriations"}
{"time":107959,"type":"word","start":1513,"end":1516,"value":"Act"}
{"time":108544,"type":"word","start":1518,"end":1522,"value":"2023"}
{"time":109778,"type":"word","start":1524,"end":1530,"value":"Public"}
{"time":110101,"type":"word","start":1531,"end":1534,"value":"Law"}
{"time":110289,"type":"word","start":1535,"end":1542,"value":"No. 117"}
{"time":110557,"type":"word","start":1539,"end":1542,"value":"117"}
{"time":111590,"type":"word","start":1542,"end":1543,"value":"-"}
{"time":111707,"type":"word","start":1543,"end":1546,"value":"328"}
{"time":113126,"type":"word","start":1548,"end":1552,"value":"div."}
{"time":113518,"type":"word","start":1553,"end":1555,"value":"II"}
{"time":114127,"type":"word","start":1557,"end":1560,"value":"136"}
{"time":115178,"type":"word","start":1561,"end":1565,"value":"Stat"}
{"time":116056,"type":"word","start":1567,"end":1571,"value":"4459"}
{"time":118321,"type":"word","start":1573,"end":1577,"value":"2022"}
{"time":119698,"type":"word","start":1580,"end":1581,"value":"5"}
{"time":120747,"type":"word","start":1583,"end":1592,"value":"Americans"}
{"time":121331,"type":"word","start":1593,"end":1597,"value":"with"}
{"time":121451,"type":"word","start":1598,"end":1610,"value":"Disabilities"}
{"time":122162,"type":"word","start":1611,"end":1614,"value":"Act"}
{"time":122362,"type":"word","start":1615,"end":1617,"value":"of"}
{"time":122439,"type":"word","start":1618,"end":1622,"value":"1990"}
{"time":123496,"type":"word","start":1624,"end":1626,"value":"42"}
{"time":124015,"type":"word","start":1627,"end":1632,"value":"U.S.C"}
{"time":124618,"type":"word","start":1634,"end":1636,"value":"§"}
{"time":125033,"type":"word","start":1637,"end":1642,"value":"12101"}
{"time":126410,"type":"word","start":1643,"end":1645,"value":"et"}
{"time":126534,"type":"word","start":1646,"end":1649,"value":"seq"}
{"time":127279,"type":"word","start":1651,"end":1652,"value":"6"}
{"time":128273,"type":"word","start":1654,"end":1659,"value":"Dobbs"}
{"time":128615,"type":"word","start":1660,"end":1661,"value":"v"}
{"time":129333,"type":"word","start":1663,"end":1670,"value":"Jackson"}
{"time":129766,"type":"word","start":1671,"end":1680,"value":"Women’s"}
{"time":130100,"type":"word","start":1681,"end":1687,"value":"Health"}
{"time":130351,"type":"word","start":1688,"end":1700,"value":"Organization"}
{"time":131319,"type":"word","start":1702,"end":1708,"value":"No. 19"}
{"time":131605,"type":"word","start":1706,"end":1708,"value":"19"}
{"time":132019,"type":"word","start":1708,"end":1709,"value":"-"}
{"time":132106,"type":"word","start":1709,"end":1713,"value":"1392"}
{"time":134168,"type":"word","start":1715,"end":1719,"value":"June"}
{"time":134448,"type":"word","start":1720,"end":1722,"value":"24"}
{"time":135030,"type":"word","start":1724,"end":1728,"value":"2022"}
{"time":136200,"type":"word","start":1730,"end":1741,"value":"https:\/\/www"}
{"time":138116,"type":"word","start":1730,"end":1759,"value":"https:\/\/www.supremecourt.gov\/"}
{"time":140978,"type":"word","start":1760,"end":1777,"value":"opinions\/21pdf\/19"}
{"time":143673,"type":"word","start":1777,"end":1778,"value":"-"}
{"time":143790,"type":"word","start":1778,"end":1783,"value":"1392_"}
{"time":145315,"type":"word","start":1783,"end":1791,"value":"6j37.pdf"}
{"time":147650,"type":"word","start":1793,"end":1801,"value":"accessed"}
{"time":148138,"type":"word","start":1802,"end":1807,"value":"March"}
{"time":148409,"type":"word","start":1808,"end":1809,"value":"7"}
{"time":148734,"type":"word","start":1811,"end":1815,"value":"2023"}
{"time":150175,"type":"word","start":1818,"end":1819,"value":"7"}
{"time":151233,"type":"word","start":1821,"end":1829,"value":"Employee"}
{"time":151754,"type":"word","start":1830,"end":1840,"value":"Retirement"}
{"time":152345,"type":"word","start":1841,"end":1847,"value":"Income"}
{"time":152676,"type":"word","start":1848,"end":1856,"value":"Security"}
{"time":153198,"type":"word","start":1857,"end":1860,"value":"Act"}
{"time":153441,"type":"word","start":1861,"end":1863,"value":"of"}
{"time":153518,"type":"word","start":1864,"end":1868,"value":"1974"}
{"time":154919,"type":"word","start":1870,"end":1872,"value":"29"}
{"time":155411,"type":"word","start":1873,"end":1878,"value":"U.S.C"}
{"time":155965,"type":"word","start":1880,"end":1882,"value":"Ch"}
{"time":157039,"type":"word","start":1884,"end":1886,"value":"18"}
{"time":157437,"type":"word","start":1887,"end":1889,"value":"§"}
{"time":157850,"type":"word","start":1890,"end":1894,"value":"1001"}
{"time":158665,"type":"word","start":1895,"end":1897,"value":"et"}
{"time":158789,"type":"word","start":1898,"end":1901,"value":"seq"}
{"time":159568,"type":"word","start":1903,"end":1904,"value":"8"}
{"time":160404,"type":"word","start":1906,"end":1915,"value":"Religious"}
{"time":160894,"type":"word","start":1916,"end":1923,"value":"Freedom"}
{"time":161257,"type":"word","start":1924,"end":1935,"value":"Restoration"}
{"time":161837,"type":"word","start":1936,"end":1939,"value":"Act"}
{"time":162078,"type":"word","start":1940,"end":1942,"value":"of"}
{"time":162145,"type":"word","start":1943,"end":1947,"value":"1993"}
{"time":163442,"type":"word","start":1949,"end":1951,"value":"42"}
{"time":163944,"type":"word","start":1952,"end":1957,"value":"U.S.C"}
{"time":164547,"type":"word","start":1959,"end":1961,"value":"Ch"}
{"time":165621,"type":"word","start":1963,"end":1966,"value":"21B"}
{"time":166332,"type":"word","start":1967,"end":1969,"value":"§"}
{"time":166746,"type":"word","start":1970,"end":1976,"value":"2000bb"}
{"time":167618,"type":"word","start":1977,"end":1979,"value":"et"}
{"time":167736,"type":"word","start":1980,"end":1983,"value":"seq"}
{"time":168470,"type":"word","start":1985,"end":1986,"value":"9"}
{"time":169519,"type":"word","start":1988,"end":1992,"value":"Fair"}
{"time":169807,"type":"word","start":1993,"end":1998,"value":"Labor"}
{"time":170126,"type":"word","start":1999,"end":2008,"value":"Standards"}
{"time":170696,"type":"word","start":2009,"end":2012,"value":"Act"}
{"time":170888,"type":"word","start":2013,"end":2015,"value":"of"}
{"time":170978,"type":"word","start":2016,"end":2020,"value":"1938"}
{"time":172247,"type":"word","start":2022,"end":2024,"value":"29"}
{"time":172818,"type":"word","start":2025,"end":2030,"value":"U.S.C"}
{"time":173329,"type":"word","start":2032,"end":2034,"value":"§"}
{"time":173785,"type":"word","start":2035,"end":2038,"value":"203"}
{"time":175079,"type":"word","start":2040,"end":2042,"value":"10"}
{"time":175895,"type":"word","start":2044,"end":2054,"value":"Department"}
{"time":176360,"type":"word","start":2055,"end":2057,"value":"of"}
{"time":176478,"type":"word","start":2058,"end":2063,"value":"Labor"}
{"time":177073,"type":"word","start":2065,"end":2074,"value":"Promoting"}
{"time":177523,"type":"word","start":2075,"end":2085,"value":"Regulatory"}
{"time":178182,"type":"word","start":2086,"end":2094,"value":"Openness"}
{"time":178672,"type":"word","start":2095,"end":2102,"value":"Through"}
{"time":178840,"type":"word","start":2103,"end":2107,"value":"Good"}
{"time":179078,"type":"word","start":2108,"end":2116,"value":"Guidance"}
{"time":179768,"type":"word","start":2118,"end":2125,"value":"Federal"}
{"time":180165,"type":"word","start":2126,"end":2134,"value":"Register"}
{"time":180931,"type":"word","start":2136,"end":2140,"value":"Vol."}
{"time":181312,"type":"word","start":2141,"end":2143,"value":"85"}
{"time":182199,"type":"word","start":2145,"end":2147,"value":"No"}
{"time":182984,"type":"word","start":2149,"end":2152,"value":"168"}
{"time":184451,"type":"word","start":2154,"end":2160,"value":"August"}
{"time":184766,"type":"word","start":2161,"end":2163,"value":"28"}
{"time":185240,"type":"word","start":2165,"end":2169,"value":"2020"}
{"time":186261,"type":"word","start":2171,"end":2182,"value":"https:\/\/www"}
{"time":188197,"type":"word","start":2171,"end":2206,"value":"https:\/\/www.govinfo.gov\/content\/pkg"}
{"time":192389,"type":"word","start":2207,"end":2210,"value":"FR-"}
{"time":192704,"type":"word","start":2210,"end":2229,"value":"2020-08-28\/pdf\/2020"}
{"time":196068,"type":"word","start":2229,"end":2230,"value":"-"}
{"time":196180,"type":"word","start":2230,"end":2239,"value":"18500.pdf"}
{"time":198363,"type":"word","start":2241,"end":2249,"value":"accessed"}
{"time":198851,"type":"word","start":2250,"end":2255,"value":"March"}
{"time":199122,"type":"word","start":2256,"end":2257,"value":"7"}
{"time":199447,"type":"word","start":2259,"end":2263,"value":"2023"}
{"time":200888,"type":"word","start":2266,"end":2268,"value":"11"}
{"time":201949,"type":"word","start":2270,"end":2284,"value":"Administrative"}
{"time":202607,"type":"word","start":2285,"end":2294,"value":"Procedure"}
{"time":203173,"type":"word","start":2295,"end":2298,"value":"Act"}
{"time":203746,"type":"word","start":2300,"end":2301,"value":"5"}
{"time":204107,"type":"word","start":2302,"end":2307,"value":"U.S.C"}
{"time":204647,"type":"word","start":2309,"end":2311,"value":"Ch"}
{"time":205721,"type":"word","start":2313,"end":2314,"value":"5"}
{"time":206570,"type":"word","start":2316,"end":2326,"value":"subchapter"}
{"time":207235,"type":"word","start":2327,"end":2328,"value":"1"}
{"time":207867,"type":"word","start":2330,"end":2332,"value":"§"}
{"time":208277,"type":"word","start":2333,"end":2336,"value":"500"}
{"time":208834,"type":"word","start":2337,"end":2339,"value":"et"}
{"time":208956,"type":"word","start":2340,"end":2343,"value":"seq"}
{"time":209710,"type":"word","start":2345,"end":2347,"value":"12"}
{"time":210751,"type":"word","start":2349,"end":2359,"value":"Regulatory"}
{"time":211346,"type":"word","start":2360,"end":2371,"value":"Flexibility"}
{"time":212084,"type":"word","start":2372,"end":2375,"value":"Act"}
{"time":212574,"type":"word","start":2377,"end":2378,"value":"5"}
{"time":212935,"type":"word","start":2379,"end":2384,"value":"U.S.C"}
{"time":213475,"type":"word","start":2386,"end":2388,"value":"Ch"}
{"time":214549,"type":"word","start":2390,"end":2391,"value":"6"}
{"time":214857,"type":"word","start":2392,"end":2394,"value":"§"}
{"time":215229,"type":"word","start":2395,"end":2398,"value":"601"}
{"time":215972,"type":"word","start":2399,"end":2401,"value":"et"}
{"time":216106,"type":"word","start":2402,"end":2405,"value":"seq"}
{"time":216861,"type":"word","start":2407,"end":2409,"value":"13"}
{"time":218042,"type":"word","start":2411,"end":2417,"value":"Donald"}
{"time":218465,"type":"word","start":2418,"end":2420,"value":"J."}
{"time":218665,"type":"word","start":2421,"end":2426,"value":"Trump"}
{"time":219294,"type":"word","start":2428,"end":2437,"value":"Executive"}
{"time":219852,"type":"word","start":2438,"end":2443,"value":"Order"}
{"time":220073,"type":"word","start":2444,"end":2449,"value":"13932"}
{"time":222315,"type":"word","start":2454,"end":2465,"value":"Modernizing"}
{"time":223066,"type":"word","start":2466,"end":2469,"value":"and"}
{"time":223188,"type":"word","start":2470,"end":2479,"value":"Reforming"}
{"time":223687,"type":"word","start":2480,"end":2483,"value":"the"}
{"time":223785,"type":"word","start":2484,"end":2494,"value":"Assessment"}
{"time":224258,"type":"word","start":2495,"end":2498,"value":"and"}
{"time":224365,"type":"word","start":2499,"end":2505,"value":"Hiring"}
{"time":224777,"type":"word","start":2506,"end":2508,"value":"of"}
{"time":224871,"type":"word","start":2509,"end":2516,"value":"Federal"}
{"time":225250,"type":"word","start":2517,"end":2520,"value":"Job"}
{"time":225571,"type":"word","start":2521,"end":2531,"value":"Candidates"}
{"time":226421,"type":"word","start":2536,"end":2543,"value":"Federal"}
{"time":226819,"type":"word","start":2544,"end":2552,"value":"Register"}
{"time":227585,"type":"word","start":2554,"end":2558,"value":"Vol."}
{"time":227966,"type":"word","start":2559,"end":2561,"value":"85"}
{"time":228886,"type":"word","start":2563,"end":2570,"value":"No. 187"}
{"time":229141,"type":"word","start":2567,"end":2570,"value":"187"}
{"time":230546,"type":"word","start":2572,"end":2576,"value":"July"}
{"time":230851,"type":"word","start":2577,"end":2578,"value":"1"}
{"time":231179,"type":"word","start":2580,"end":2584,"value":"2020"}
{"time":232160,"type":"word","start":2586,"end":2598,"value":"pp. 39457–"}
{"time":232530,"type":"word","start":2590,"end":2595,"value":"39457"}
{"time":234781,"type":"word","start":2586,"end":2598,"value":"pp. 39457–"}
{"time":234863,"type":"word","start":2598,"end":2603,"value":"39459"}
{"time":237392,"type":"word","start":2605,"end":2616,"value":"https:\/\/www"}
{"time":239473,"type":"word","start":2605,"end":2632,"value":"https:\/\/www.federalregister"}
{"time":242244,"type":"word","start":2634,"end":2663,"value":"gov\/documents\/2020\/07\/01\/2020"}
{"time":246945,"type":"word","start":2663,"end":2664,"value":"-"}
{"time":247059,"type":"word","start":2664,"end":2733,"value":"14337\/modernizing-and-reforming-the-assessment-and-hiring-of-federal-"}
{"time":251558,"type":"word","start":2734,"end":2748,"value":"job-candidates"}
{"time":252730,"type":"word","start":2750,"end":2758,"value":"accessed"}
{"time":253201,"type":"word","start":2759,"end":2764,"value":"March"}
{"time":253467,"type":"word","start":2765,"end":2766,"value":"7"}
{"time":253841,"type":"word","start":2768,"end":2772,"value":"2023"}
{"time":255309,"type":"word","start":2775,"end":2777,"value":"14"}
{"time":256488,"type":"word","start":2779,"end":2788,"value":"Workforce"}
{"time":257078,"type":"word","start":2789,"end":2799,"value":"Investment"}
{"time":257573,"type":"word","start":2800,"end":2803,"value":"and"}
{"time":257664,"type":"word","start":2804,"end":2815,"value":"Opportunity"}
{"time":258311,"type":"word","start":2816,"end":2819,"value":"Act"}
{"time":258801,"type":"word","start":2821,"end":2827,"value":"Public"}
{"time":259118,"type":"word","start":2828,"end":2831,"value":"Law"}
{"time":259278,"type":"word","start":2832,"end":2835,"value":"113"}
{"time":260277,"type":"word","start":2835,"end":2836,"value":"-"}
{"time":260375,"type":"word","start":2836,"end":2839,"value":"128"}
{"time":262006,"type":"word","start":2841,"end":2843,"value":"15"}
{"time":263100,"type":"word","start":2845,"end":2856,"value":"Coronavirus"}
{"time":263878,"type":"word","start":2857,"end":2860,"value":"Aid"}
{"time":264372,"type":"word","start":2862,"end":2868,"value":"Relief"}
{"time":265054,"type":"word","start":2870,"end":2873,"value":"and"}
{"time":265199,"type":"word","start":2874,"end":2882,"value":"Economic"}
{"time":265696,"type":"word","start":2883,"end":2891,"value":"Security"}
{"time":266630,"type":"word","start":2893,"end":2898,"value":"CARES"}
{"time":267347,"type":"word","start":2900,"end":2903,"value":"Act"}
{"time":267967,"type":"word","start":2905,"end":2911,"value":"S.3548"}
{"time":269822,"type":"word","start":2913,"end":2918,"value":"116th"}
{"time":270798,"type":"word","start":2919,"end":2927,"value":"Congress"}
{"time":271630,"type":"word","start":2929,"end":2932,"value":"2nd"}
{"time":272003,"type":"word","start":2933,"end":2937,"value":"Sess"}
{"time":272855,"type":"word","start":2939,"end":2941,"value":"16"}
{"time":274081,"type":"word","start":2943,"end":2950,"value":"Federal"}
{"time":274478,"type":"word","start":2951,"end":2963,"value":"Unemployment"}
{"time":275075,"type":"word","start":2964,"end":2967,"value":"Tax"}
{"time":275451,"type":"word","start":2968,"end":2971,"value":"Act"}
{"time":276043,"type":"word","start":2973,"end":2978,"value":"I.R.C"}
{"time":277162,"type":"word","start":2981,"end":2983,"value":"Ch"}
{"time":278244,"type":"word","start":2985,"end":2987,"value":"23"}
{"time":279392,"type":"word","start":2989,"end":2991,"value":"17"}
{"time":280674,"type":"word","start":2993,"end":3001,"value":"American"}
{"time":281154,"type":"word","start":3002,"end":3008,"value":"Rescue"}
{"time":281558,"type":"word","start":3009,"end":3013,"value":"Plan"}
{"time":281914,"type":"word","start":3014,"end":3017,"value":"Act"}
{"time":282163,"type":"word","start":3018,"end":3020,"value":"of"}
{"time":282249,"type":"word","start":3021,"end":3025,"value":"2021"}
{"time":283513,"type":"word","start":3027,"end":3028,"value":"P"}
