{"time":6,"type":"word","start":0,"end":8,"value":"stration"}
{"time":445,"type":"word","start":9,"end":11,"value":"of"}
{"time":545,"type":"word","start":12,"end":15,"value":"Our"}
{"time":711,"type":"word","start":16,"end":27,"value":"Immigration"}
{"time":1202,"type":"word","start":28,"end":32,"value":"Laws"}
{"time":2062,"type":"word","start":34,"end":42,"value":"Although"}
{"time":2315,"type":"word","start":43,"end":46,"value":"its"}
{"time":2473,"type":"word","start":47,"end":51,"value":"role"}
{"time":2688,"type":"word","start":52,"end":55,"value":"has"}
{"time":2860,"type":"word","start":56,"end":63,"value":"changed"}
{"time":3255,"type":"word","start":64,"end":68,"value":"over"}
{"time":3411,"type":"word","start":69,"end":72,"value":"the"}
{"time":3501,"type":"word","start":73,"end":78,"value":"years"}
{"time":4162,"type":"word","start":80,"end":84,"value":"most"}
{"time":4453,"type":"word","start":85,"end":92,"value":"notably"}
{"time":4898,"type":"word","start":93,"end":102,"value":"following"}
{"time":5351,"type":"word","start":103,"end":106,"value":"the"}
{"time":5428,"type":"word","start":107,"end":114,"value":"passage"}
{"time":5863,"type":"word","start":115,"end":117,"value":"of"}
{"time":5928,"type":"word","start":118,"end":121,"value":"the"}
{"time":6026,"type":"word","start":122,"end":130,"value":"Homeland"}
{"time":6535,"type":"word","start":131,"end":139,"value":"Security"}
{"time":7097,"type":"word","start":140,"end":143,"value":"Act"}
{"time":7316,"type":"word","start":144,"end":146,"value":"of"}
{"time":7411,"type":"word","start":147,"end":154,"value":"2002,93"}
{"time":8958,"type":"word","start":155,"end":158,"value":"the"}
{"time":9074,"type":"word","start":159,"end":169,"value":"Department"}
{"time":9530,"type":"word","start":170,"end":172,"value":"of"}
{"time":9638,"type":"word","start":173,"end":180,"value":"Justice"}
{"time":10078,"type":"word","start":181,"end":186,"value":"plays"}
{"time":10413,"type":"word","start":187,"end":188,"value":"a"}
{"time":10465,"type":"word","start":189,"end":196,"value":"crucial"}
{"time":10834,"type":"word","start":197,"end":201,"value":"role"}
{"time":11100,"type":"word","start":202,"end":204,"value":"in"}
{"time":11180,"type":"word","start":205,"end":208,"value":"the"}
{"time":11293,"type":"word","start":209,"end":220,"value":"enforcement"}
{"time":11841,"type":"word","start":221,"end":224,"value":"and"}
{"time":11929,"type":"word","start":225,"end":237,"value":"adjudication"}
{"time":12634,"type":"word","start":238,"end":240,"value":"of"}
{"time":12737,"type":"word","start":241,"end":244,"value":"our"}
{"time":12885,"type":"word","start":245,"end":256,"value":"immigration"}
{"time":13386,"type":"word","start":257,"end":264,"value":"laws.94"}
{"time":14565,"type":"word","start":265,"end":268,"value":"Its"}
{"time":14713,"type":"word","start":269,"end":279,"value":"leadership"}
{"time":15254,"type":"word","start":280,"end":283,"value":"and"}
{"time":15405,"type":"word","start":284,"end":290,"value":"energy"}
{"time":16055,"type":"word","start":292,"end":299,"value":"however"}
{"time":16757,"type":"word","start":301,"end":305,"value":"have"}
{"time":16952,"type":"word","start":306,"end":309,"value":"not"}
{"time":17179,"type":"word","start":310,"end":316,"value":"always"}
{"time":17496,"type":"word","start":317,"end":326,"value":"reflected"}
{"time":17997,"type":"word","start":327,"end":330,"value":"the"}
{"time":18109,"type":"word","start":331,"end":341,"value":"importance"}
{"time":18656,"type":"word","start":342,"end":348,"value":"placed"}
{"time":19000,"type":"word","start":349,"end":351,"value":"by"}
{"time":19143,"type":"word","start":352,"end":360,"value":"Congress"}
{"time":19652,"type":"word","start":361,"end":363,"value":"on"}
{"time":19752,"type":"word","start":364,"end":367,"value":"the"}
{"time":19888,"type":"word","start":368,"end":377,"value":"execution"}
{"time":20474,"type":"word","start":378,"end":380,"value":"of"}
{"time":20575,"type":"word","start":381,"end":385,"value":"that"}
{"time":20745,"type":"word","start":386,"end":393,"value":"crucial"}
{"time":21137,"type":"word","start":394,"end":401,"value":"mission"}
{"time":22001,"type":"word","start":403,"end":407,"value":"With"}
{"time":22167,"type":"word","start":408,"end":409,"value":"a"}
{"time":22221,"type":"word","start":410,"end":413,"value":"few"}
{"time":22461,"type":"word","start":414,"end":421,"value":"notable"}
{"time":22881,"type":"word","start":422,"end":432,"value":"exceptions"}
{"time":23770,"type":"word","start":434,"end":444,"value":"successful"}
{"time":24362,"type":"word","start":445,"end":456,"value":"fulfillment"}
{"time":24944,"type":"word","start":457,"end":459,"value":"of"}
{"time":25047,"type":"word","start":460,"end":463,"value":"the"}
{"time":25124,"type":"word","start":464,"end":478,"value":"department’s"}
{"time":25692,"type":"word","start":479,"end":495,"value":"responsibilities"}
{"time":26647,"type":"word","start":496,"end":500,"value":"with"}
{"time":26827,"type":"word","start":501,"end":508,"value":"respect"}
{"time":27254,"type":"word","start":509,"end":511,"value":"to"}
{"time":27392,"type":"word","start":512,"end":517,"value":"immi-"}
{"time":27580,"type":"word","start":518,"end":525,"value":"gration"}
{"time":27985,"type":"word","start":526,"end":529,"value":"was"}
{"time":28164,"type":"word","start":530,"end":537,"value":"largely"}
{"time":28616,"type":"word","start":538,"end":547,"value":"neglected"}
{"time":29113,"type":"word","start":548,"end":553,"value":"until"}
{"time":29374,"type":"word","start":554,"end":557,"value":"the"}
{"time":29455,"type":"word","start":558,"end":563,"value":"Trump"}
{"time":29741,"type":"word","start":564,"end":578,"value":"Administration"}
{"time":31035,"type":"word","start":580,"end":583,"value":"The"}
{"time":31146,"type":"word","start":584,"end":594,"value":"Department"}
{"time":31652,"type":"word","start":595,"end":597,"value":"of"}
{"time":31760,"type":"word","start":598,"end":606,"value":"Homeland"}
{"time":32251,"type":"word","start":607,"end":615,"value":"Security"}
{"time":32785,"type":"word","start":616,"end":619,"value":"may"}
{"time":32983,"type":"word","start":620,"end":622,"value":"be"}
{"time":33104,"type":"word","start":623,"end":626,"value":"the"}
{"time":33194,"type":"word","start":627,"end":634,"value":"largest"}
{"time":33682,"type":"word","start":635,"end":642,"value":"federal"}
{"time":34043,"type":"word","start":643,"end":653,"value":"department"}
{"time":34543,"type":"word","start":654,"end":658,"value":"with"}
{"time":34723,"type":"word","start":659,"end":670,"value":"immigration"}
{"time":35264,"type":"word","start":671,"end":687,"value":"responsibilities"}
{"time":36493,"type":"word","start":689,"end":692,"value":"but"}
{"time":36678,"type":"word","start":693,"end":703,"value":"successful"}
{"time":37278,"type":"word","start":704,"end":715,"value":"fulfillment"}
{"time":37872,"type":"word","start":716,"end":718,"value":"of"}
{"time":37938,"type":"word","start":719,"end":722,"value":"the"}
{"time":38028,"type":"word","start":723,"end":739,"value":"responsibilities"}
{"time":38984,"type":"word","start":740,"end":750,"value":"prescribed"}
{"time":39578,"type":"word","start":751,"end":753,"value":"by"}
{"time":39718,"type":"word","start":754,"end":757,"value":"the"}
{"time":39860,"type":"word","start":758,"end":769,"value":"immigration"}
{"time":40353,"type":"word","start":770,"end":774,"value":"laws"}
{"time":40709,"type":"word","start":775,"end":777,"value":"is"}
{"time":40839,"type":"word","start":778,"end":781,"value":"not"}
{"time":41085,"type":"word","start":782,"end":790,"value":"possible"}
{"time":41598,"type":"word","start":791,"end":798,"value":"without"}
{"time":41926,"type":"word","start":799,"end":803,"value":"bold"}
{"time":42149,"type":"word","start":804,"end":807,"value":"and"}
{"time":42249,"type":"word","start":808,"end":817,"value":"dedicated"}
{"time":42797,"type":"word","start":818,"end":824,"value":"action"}
{"time":43198,"type":"word","start":825,"end":827,"value":"by"}
{"time":43334,"type":"word","start":828,"end":831,"value":"the"}
{"time":43431,"type":"word","start":832,"end":842,"value":"Department"}
{"time":43934,"type":"word","start":843,"end":845,"value":"of"}
{"time":44026,"type":"word","start":846,"end":853,"value":"Justice"}
{"time":45005,"type":"word","start":855,"end":858,"value":"The"}
{"time":45123,"type":"word","start":859,"end":862,"value":"DOJ"}
{"time":45771,"type":"word","start":863,"end":866,"value":"and"}
{"time":45908,"type":"word","start":867,"end":870,"value":"its"}
{"time":46045,"type":"word","start":871,"end":881,"value":"leadership"}
{"time":46558,"type":"word","start":882,"end":886,"value":"must"}
{"time":46822,"type":"word","start":887,"end":900,"value":"intentionally"}
{"time":47457,"type":"word","start":901,"end":911,"value":"prioritize"}
{"time":48119,"type":"word","start":912,"end":923,"value":"fulfillment"}
{"time":48684,"type":"word","start":924,"end":926,"value":"of"}
{"time":48788,"type":"word","start":927,"end":930,"value":"the"}
{"time":48865,"type":"word","start":931,"end":945,"value":"department’s"}
{"time":49463,"type":"word","start":946,"end":965,"value":"immigration-related"}
{"time":50381,"type":"word","start":966,"end":982,"value":"responsibilities"}
{"time":51367,"type":"word","start":983,"end":985,"value":"in"}
{"time":51434,"type":"word","start":986,"end":989,"value":"the"}
{"time":51509,"type":"word","start":990,"end":994,"value":"next"}
{"time":51811,"type":"word","start":995,"end":1007,"value":"conservative"}
{"time":52458,"type":"word","start":1008,"end":1014,"value":"Admin-"}
{"time":52790,"type":"word","start":1015,"end":1024,"value":"istration"}
{"time":53869,"type":"word","start":1026,"end":1030,"value":"This"}
{"time":54066,"type":"word","start":1031,"end":1035,"value":"will"}
{"time":54199,"type":"word","start":1036,"end":1038,"value":"be"}
{"time":54326,"type":"word","start":1039,"end":1041,"value":"no"}
{"time":54557,"type":"word","start":1042,"end":1047,"value":"small"}
{"time":54897,"type":"word","start":1048,"end":1052,"value":"task"}
{"time":55600,"type":"word","start":1054,"end":1056,"value":"as"}
{"time":55795,"type":"word","start":1057,"end":1062,"value":"these"}
{"time":56012,"type":"word","start":1063,"end":1079,"value":"responsibilities"}
{"time":57003,"type":"word","start":1080,"end":1084,"value":"play"}
{"time":57270,"type":"word","start":1085,"end":1088,"value":"out"}
{"time":57391,"type":"word","start":1089,"end":1095,"value":"across"}
{"time":57781,"type":"word","start":1096,"end":1102,"value":"nearly"}
{"time":58109,"type":"word","start":1103,"end":1108,"value":"every"}
{"time":58310,"type":"word","start":1109,"end":1112,"value":"DOJ"}
{"time":58886,"type":"word","start":1113,"end":1119,"value":"office"}
{"time":59229,"type":"word","start":1120,"end":1123,"value":"and"}
{"time":59338,"type":"word","start":1124,"end":1133,"value":"component"}
{"time":60350,"type":"word","start":1135,"end":1137,"value":"If"}
{"time":60525,"type":"word","start":1138,"end":1142,"value":"they"}
{"time":60640,"type":"word","start":1143,"end":1147,"value":"hope"}
{"time":60890,"type":"word","start":1148,"end":1150,"value":"to"}
{"time":60969,"type":"word","start":1151,"end":1158,"value":"fulfill"}
{"time":61403,"type":"word","start":1159,"end":1164,"value":"their"}
{"time":61523,"type":"word","start":1165,"end":1181,"value":"responsibilities"}
{"time":62575,"type":"word","start":1182,"end":1184,"value":"as"}
{"time":62699,"type":"word","start":1185,"end":1193,"value":"assigned"}
{"time":63072,"type":"word","start":1194,"end":1196,"value":"by"}
{"time":63242,"type":"word","start":1197,"end":1205,"value":"Congress"}
{"time":63749,"type":"word","start":1206,"end":1209,"value":"and"}
{"time":63859,"type":"word","start":1210,"end":1217,"value":"deliver"}
{"time":64198,"type":"word","start":1218,"end":1225,"value":"results"}
{"time":64672,"type":"word","start":1226,"end":1229,"value":"for"}
{"time":64824,"type":"word","start":1230,"end":1233,"value":"the"}
{"time":64949,"type":"word","start":1234,"end":1242,"value":"American"}
{"time":65369,"type":"word","start":1243,"end":1249,"value":"people"}
{"time":65998,"type":"word","start":1251,"end":1254,"value":"the"}
{"time":66070,"type":"word","start":1255,"end":1265,"value":"department"}
{"time":66591,"type":"word","start":1266,"end":1269,"value":"and"}
{"time":66676,"type":"word","start":1270,"end":1273,"value":"the"}
{"time":66782,"type":"word","start":1274,"end":1282,"value":"Attorney"}
{"time":67139,"type":"word","start":1283,"end":1290,"value":"General"}
{"time":67555,"type":"word","start":1291,"end":1297,"value":"should"}
{"time":68092,"type":"word","start":1299,"end":1300,"value":"l"}
{"time":68239,"type":"word","start":1301,"end":1306,"value":"Issue"}
{"time":68478,"type":"word","start":1307,"end":1315,"value":"guidance"}
{"time":68907,"type":"word","start":1316,"end":1318,"value":"to"}
{"time":69072,"type":"word","start":1319,"end":1322,"value":"all"}
{"time":69240,"type":"word","start":1323,"end":1326,"value":"U.S"}
{"time":69615,"type":"word","start":1328,"end":1337,"value":"Attorneys"}
{"time":70091,"type":"word","start":1338,"end":1349,"value":"emphasizing"}
{"time":70733,"type":"word","start":1350,"end":1353,"value":"the"}
{"time":70882,"type":"word","start":1354,"end":1364,"value":"importance"}
{"time":71407,"type":"word","start":1365,"end":1367,"value":"of"}
{"time":71483,"type":"word","start":1368,"end":1379,"value":"prosecuting"}
{"time":72166,"type":"word","start":1380,"end":1391,"value":"immigration"}
{"time":72653,"type":"word","start":1392,"end":1400,"value":"offenses"}
{"time":73463,"type":"word","start":1401,"end":1403,"value":"95"}
{"time":74177,"type":"word","start":1404,"end":1407,"value":"and"}
{"time":74308,"type":"word","start":1408,"end":1427,"value":"immigration-related"}
{"time":75251,"type":"word","start":1428,"end":1436,"value":"offenses"}
{"time":76273,"type":"word","start":1438,"end":1441,"value":"The"}
{"time":76369,"type":"word","start":1442,"end":1447,"value":"brunt"}
{"time":76617,"type":"word","start":1448,"end":1450,"value":"of"}
{"time":76697,"type":"word","start":1451,"end":1456,"value":"these"}
{"time":76922,"type":"word","start":1457,"end":1465,"value":"offenses"}
{"time":77412,"type":"word","start":1466,"end":1468,"value":"is"}
{"time":77553,"type":"word","start":1469,"end":1473,"value":"born"}
{"time":77838,"type":"word","start":1474,"end":1476,"value":"by"}
{"time":78024,"type":"word","start":1477,"end":1486,"value":"districts"}
{"time":78508,"type":"word","start":1487,"end":1492,"value":"along"}
{"time":78824,"type":"word","start":1493,"end":1496,"value":"the"}
{"time":78899,"type":"word","start":1497,"end":1509,"value":"southwestern"}
{"time":79615,"type":"word","start":1510,"end":1516,"value":"border"}
{"time":79870,"type":"word","start":1517,"end":1521,"value":"with"}
{"time":80085,"type":"word","start":1522,"end":1528,"value":"Mexico"}
{"time":80920,"type":"word","start":1530,"end":1533,"value":"but"}
{"time":81134,"type":"word","start":1534,"end":1537,"value":"the"}
{"time":81206,"type":"word","start":1538,"end":1544,"value":"simple"}
{"time":81543,"type":"word","start":1545,"end":1549,"value":"fact"}
{"time":81869,"type":"word","start":1550,"end":1557,"value":"remains"}
{"time":82291,"type":"word","start":1558,"end":1562,"value":"that"}
{"time":82442,"type":"word","start":1563,"end":1574,"value":"immigration"}
{"time":82953,"type":"word","start":1575,"end":1578,"value":"and"}
{"time":83052,"type":"word","start":1579,"end":1598,"value":"immigration-related"}
{"time":83956,"type":"word","start":1599,"end":1607,"value":"offenses"}
{"time":84470,"type":"word","start":1608,"end":1611,"value":"are"}
{"time":84577,"type":"word","start":1612,"end":1619,"value":"present"}
{"time":84963,"type":"word","start":1620,"end":1622,"value":"in"}
{"time":85049,"type":"word","start":1623,"end":1628,"value":"every"}
{"time":85270,"type":"word","start":1629,"end":1637,"value":"district"}
{"time":85706,"type":"word","start":1638,"end":1644,"value":"across"}
{"time":86086,"type":"word","start":1645,"end":1648,"value":"the"}
{"time":86176,"type":"word","start":1649,"end":1656,"value":"country"}
{"time":87122,"type":"word","start":1658,"end":1670,"value":"Successfully"}
{"time":87793,"type":"word","start":1671,"end":1679,"value":"pursuing"}
{"time":88287,"type":"word","start":1680,"end":1683,"value":"the"}
{"time":88373,"type":"word","start":1684,"end":1694,"value":"priorities"}
{"time":88946,"type":"word","start":1695,"end":1703,"value":"outlined"}
{"time":89391,"type":"word","start":1704,"end":1706,"value":"in"}
{"time":89473,"type":"word","start":1707,"end":1711,"value":"this"}
{"time":89628,"type":"word","start":1712,"end":1719,"value":"chapter"}
{"time":90011,"type":"word","start":1720,"end":1724,"value":"will"}
{"time":90217,"type":"word","start":1725,"end":1732,"value":"require"}
{"time":90663,"type":"word","start":1733,"end":1741,"value":"creative"}
{"time":91100,"type":"word","start":1742,"end":1745,"value":"use"}
{"time":91414,"type":"word","start":1746,"end":1748,"value":"of"}
{"time":91489,"type":"word","start":1749,"end":1752,"value":"the"}
{"time":91569,"type":"word","start":1753,"end":1760,"value":"various"}
{"time":92017,"type":"word","start":1761,"end":1772,"value":"immigration"}
{"time":92563,"type":"word","start":1773,"end":1776,"value":"and"}
{"time":92688,"type":"word","start":1777,"end":1796,"value":"immigration-related"}
{"time":93604,"type":"word","start":1797,"end":1808,"value":"authorities"}
{"time":94201,"type":"word","start":1809,"end":1811,"value":"in"}
{"time":94303,"type":"word","start":1812,"end":1817,"value":"close"}
{"time":94589,"type":"word","start":1818,"end":1829,"value":"partnership"}
{"time":95246,"type":"word","start":1830,"end":1834,"value":"with"}
{"time":95367,"type":"word","start":1835,"end":1838,"value":"the"}
{"time":95458,"type":"word","start":1839,"end":1849,"value":"Department"}
{"time":95936,"type":"word","start":1850,"end":1852,"value":"of"}
{"time":96023,"type":"word","start":1853,"end":1861,"value":"Homeland"}
{"time":96531,"type":"word","start":1862,"end":1870,"value":"Security"}
{"time":97310,"type":"word","start":1872,"end":1875,"value":"the"}
{"time":97401,"type":"word","start":1876,"end":1886,"value":"Department"}
{"time":97897,"type":"word","start":1887,"end":1889,"value":"of"}
{"time":97977,"type":"word","start":1890,"end":1895,"value":"State"}
{"time":98598,"type":"word","start":1897,"end":1900,"value":"and"}
{"time":98754,"type":"word","start":1901,"end":1906,"value":"other"}
{"time":98980,"type":"word","start":1907,"end":1918,"value":"appropriate"}
{"time":99534,"type":"word","start":1919,"end":1926,"value":"federal"}
{"time":99931,"type":"word","start":1927,"end":1935,"value":"entities"}
{"time":100277,"type":"word","start":1936,"end":1945,"value":"depending"}
{"time":100734,"type":"word","start":1946,"end":1948,"value":"on"}
{"time":100845,"type":"word","start":1949,"end":1952,"value":"the"}
{"time":100931,"type":"word","start":1953,"end":1962,"value":"situation"}
{"time":102113,"type":"word","start":1964,"end":1965,"value":"l"}
{"time":102258,"type":"word","start":1966,"end":1972,"value":"Pursue"}
{"time":102580,"type":"word","start":1973,"end":1984,"value":"appropriate"}
{"time":103103,"type":"word","start":1985,"end":1990,"value":"steps"}
{"time":103474,"type":"word","start":1991,"end":1993,"value":"to"}
{"time":103586,"type":"word","start":1994,"end":2000,"value":"assist"}
{"time":103902,"type":"word","start":2001,"end":2004,"value":"the"}
{"time":103992,"type":"word","start":2005,"end":2015,"value":"Department"}
{"time":104501,"type":"word","start":2016,"end":2018,"value":"of"}
{"time":104576,"type":"word","start":2019,"end":2027,"value":"Homeland"}
{"time":105061,"type":"word","start":2028,"end":2036,"value":"Security"}
{"time":105625,"type":"word","start":2037,"end":2039,"value":"in"}
{"time":105713,"type":"word","start":2040,"end":2049,"value":"obtaining"}
{"time":106145,"type":"word","start":2050,"end":2061,"value":"information"}
{"time":106658,"type":"word","start":2062,"end":2067,"value":"about"}
{"time":106937,"type":"word","start":2068,"end":2076,"value":"criminal"}
{"time":107334,"type":"word","start":2077,"end":2083,"value":"aliens"}
{"time":107771,"type":"word","start":2084,"end":2086,"value":"in"}
{"time":107872,"type":"word","start":2087,"end":2100,"value":"jurisdictions"}
{"time":108548,"type":"word","start":2101,"end":2107,"value":"across"}
{"time":108905,"type":"word","start":2108,"end":2111,"value":"the"}
{"time":108984,"type":"word","start":2112,"end":2118,"value":"United"}
{"time":109364,"type":"word","start":2119,"end":2125,"value":"States"}
{"time":110032,"type":"word","start":2127,"end":2139,"value":"particularly"}
{"time":110636,"type":"word","start":2140,"end":2145,"value":"those"}
{"time":110938,"type":"word","start":2146,"end":2152,"value":"inside"}
{"time":111315,"type":"word","start":2156,"end":2165,"value":"sanctuary"}
{"time":111938,"type":"word","start":2169,"end":2182,"value":"jurisdictions"}
{"time":113218,"type":"word","start":2184,"end":2185,"value":"l"}
{"time":113360,"type":"word","start":2186,"end":2193,"value":"Examine"}
{"time":113771,"type":"word","start":2194,"end":2197,"value":"and"}
{"time":113910,"type":"word","start":2198,"end":2206,"value":"consider"}
{"time":114336,"type":"word","start":2207,"end":2210,"value":"the"}
{"time":114470,"type":"word","start":2211,"end":2226,"value":"appropriateness"}
{"time":115168,"type":"word","start":2227,"end":2229,"value":"of"}
{"time":115273,"type":"word","start":2230,"end":2241,"value":"withdrawing"}
{"time":115771,"type":"word","start":2242,"end":2244,"value":"or"}
{"time":115907,"type":"word","start":2245,"end":2256,"value":"overturning"}
{"time":116439,"type":"word","start":2257,"end":2262,"value":"every"}
{"time":116640,"type":"word","start":2263,"end":2274,"value":"immigration"}
{"time":117169,"type":"word","start":2275,"end":2283,"value":"decision"}
{"time":117648,"type":"word","start":2284,"end":2292,"value":"rendered"}
{"time":117943,"type":"word","start":2293,"end":2295,"value":"by"}
{"time":118112,"type":"word","start":2296,"end":2304,"value":"Attorney"}
{"time":118473,"type":"word","start":2305,"end":2312,"value":"General"}
{"time":118844,"type":"word","start":2313,"end":2320,"value":"Garland"}
{"time":119656,"type":"word","start":2322,"end":2325,"value":"and"}
{"time":119785,"type":"word","start":2326,"end":2329,"value":"any"}
{"time":119969,"type":"word","start":2330,"end":2339,"value":"successor"}
{"time":120578,"type":"word","start":2340,"end":2348,"value":"Attorney"}
{"time":120924,"type":"word","start":2349,"end":2356,"value":"General"}
{"time":121325,"type":"word","start":2357,"end":2363,"value":"during"}
{"time":121605,"type":"word","start":2364,"end":2373,"value":"President"}
{"time":122134,"type":"word","start":2374,"end":2383,"value":"Biden’s"}
{"time":122568,"type":"word","start":2384,"end":2388,"value":"term"}
{"time":123394,"type":"word","start":2391,"end":2394,"value":"The"}
{"time":123533,"type":"word","start":2395,"end":2403,"value":"Attorney"}
{"time":123873,"type":"word","start":2404,"end":2411,"value":"General"}
{"time":124237,"type":"word","start":2412,"end":2418,"value":"should"}
{"time":124443,"type":"word","start":2419,"end":2423,"value":"pick"}
{"time":124685,"type":"word","start":2424,"end":2426,"value":"up"}
{"time":124860,"type":"word","start":2427,"end":2432,"value":"where"}
{"time":124961,"type":"word","start":2433,"end":2436,"value":"the"}
{"time":125111,"type":"word","start":2437,"end":2446,"value":"Attorneys"}
{"time":125524,"type":"word","start":2447,"end":2454,"value":"General"}
{"time":125908,"type":"word","start":2455,"end":2460,"value":"under"}
{"time":126082,"type":"word","start":2461,"end":2470,"value":"President"}
{"time":126646,"type":"word","start":2471,"end":2476,"value":"Trump"}
{"time":126932,"type":"word","start":2477,"end":2481,"value":"left"}
{"time":127193,"type":"word","start":2482,"end":2485,"value":"off"}
{"time":127461,"type":"word","start":2486,"end":2489,"value":"and"}
{"time":127563,"type":"word","start":2490,"end":2498,"value":"exercise"}
{"time":128122,"type":"word","start":2499,"end":2502,"value":"his"}
{"time":128303,"type":"word","start":2503,"end":2505,"value":"or"}
{"time":128413,"type":"word","start":2506,"end":2509,"value":"her"}
{"time":128632,"type":"word","start":2510,"end":2519,"value":"authority"}
{"time":129071,"type":"word","start":2520,"end":2522,"value":"to"}
{"time":129264,"type":"word","start":2523,"end":2533,"value":"adjudicate"}
{"time":129782,"type":"word","start":2534,"end":2539,"value":"cases"}
{"time":130228,"type":"word","start":2540,"end":2543,"value":"and"}
{"time":130343,"type":"word","start":2544,"end":2551,"value":"provide"}
{"time":130735,"type":"word","start":2552,"end":2560,"value":"guidance"}
{"time":131204,"type":"word","start":2561,"end":2563,"value":"in"}
{"time":131282,"type":"word","start":2564,"end":2575,"value":"appropriate"}
{"time":131834,"type":"word","start":2576,"end":2581,"value":"cases"}
{"time":132243,"type":"word","start":2582,"end":2584,"value":"to"}
{"time":132925,"type":"word","start":2586,"end":2589,"value":"—"}
{"time":133762,"type":"word","start":2590,"end":2593,"value":"568"}
{"time":135352,"type":"word","start":2598,"end":2605,"value":"Mandate"}
{"time":135770,"type":"word","start":2606,"end":2609,"value":"for"}
{"time":135920,"type":"word","start":2610,"end":2620,"value":"Leadership"}
{"time":136693,"type":"word","start":2622,"end":2625,"value":"The"}
{"time":136785,"type":"word","start":2626,"end":2638,"value":"Conservative"}
{"time":137391,"type":"word","start":2639,"end":2646,"value":"Promise"}
{"time":137797,"type":"word","start":2647,"end":2654,"value":"correct"}
{"time":138154,"type":"word","start":2655,"end":2664,"value":"erroneous"}
{"time":138645,"type":"word","start":2665,"end":2674,"value":"decisions"}
{"time":139518,"type":"word","start":2676,"end":2683,"value":"provide"}
{"time":139846,"type":"word","start":2684,"end":2691,"value":"clarity"}
{"time":140641,"type":"word","start":2693,"end":2696,"value":"and"}
{"time":140791,"type":"word","start":2697,"end":2702,"value":"align"}
{"time":141092,"type":"word","start":2703,"end":2712,"value":"Executive"}
{"time":141608,"type":"word","start":2713,"end":2719,"value":"Office"}
{"time":141951,"type":"word","start":2720,"end":2723,"value":"for"}
{"time":142155,"type":"word","start":2724,"end":2735,"value":"Immigration"}
{"time":142656,"type":"word","start":2736,"end":2742,"value":"Review"}
{"time":143417,"type":"word","start":2744,"end":2748,"value":"EOIR"}
{"time":144386,"type":"word","start":2750,"end":2759,"value":"decisions"}
{"time":144896,"type":"word","start":2760,"end":2764,"value":"with"}
{"time":145044,"type":"word","start":2765,"end":2768,"value":"the"}
{"time":145115,"type":"word","start":2769,"end":2772,"value":"law"}
{"time":145847,"type":"word","start":2774,"end":2775,"value":"l"}
{"time":146028,"type":"word","start":2776,"end":2778,"value":"At"}
{"time":146133,"type":"word","start":2779,"end":2780,"value":"a"}
{"time":146175,"type":"word","start":2781,"end":2788,"value":"minimum"}
{"time":146917,"type":"word","start":2790,"end":2796,"value":"pursue"}
{"time":147302,"type":"word","start":2797,"end":2804,"value":"through"}
{"time":147535,"type":"word","start":2805,"end":2815,"value":"rulemaking"}
{"time":148472,"type":"word","start":2818,"end":2821,"value":"and"}
{"time":148619,"type":"word","start":2822,"end":2824,"value":"in"}
{"time":148737,"type":"word","start":2825,"end":2836,"value":"partnership"}
{"time":149349,"type":"word","start":2837,"end":2841,"value":"with"}
{"time":149473,"type":"word","start":2842,"end":2845,"value":"the"}
{"time":149547,"type":"word","start":2846,"end":2856,"value":"Department"}
{"time":150030,"type":"word","start":2857,"end":2859,"value":"of"}
{"time":150106,"type":"word","start":2860,"end":2868,"value":"Homeland"}
{"time":150597,"type":"word","start":2869,"end":2877,"value":"Security"}
{"time":151137,"type":"word","start":2878,"end":2883,"value":"where"}
{"time":151332,"type":"word","start":2884,"end":2895,"value":"appropriate"}
{"time":152190,"type":"word","start":2898,"end":2901,"value":"the"}
{"time":152283,"type":"word","start":2902,"end":2914,"value":"promulgation"}
{"time":153012,"type":"word","start":2915,"end":2917,"value":"of"}
{"time":153130,"type":"word","start":2918,"end":2923,"value":"every"}
{"time":153392,"type":"word","start":2924,"end":2928,"value":"rule"}
{"time":153648,"type":"word","start":2929,"end":2936,"value":"related"}
{"time":154043,"type":"word","start":2937,"end":2939,"value":"to"}
{"time":154173,"type":"word","start":2940,"end":2951,"value":"immigration"}
{"time":154767,"type":"word","start":2952,"end":2956,"value":"that"}
{"time":154877,"type":"word","start":2957,"end":2960,"value":"was"}
{"time":155039,"type":"word","start":2961,"end":2967,"value":"issued"}
{"time":155326,"type":"word","start":2968,"end":2974,"value":"during"}
{"time":155565,"type":"word","start":2975,"end":2978,"value":"the"}
{"time":155622,"type":"word","start":2979,"end":2984,"value":"Trump"}
{"time":155909,"type":"word","start":2985,"end":2999,"value":"Administration"}
{"time":157203,"type":"word","start":3001,"end":3005,"value":"Such"}
{"time":157492,"type":"word","start":3006,"end":3017,"value":"rulemakings"}
